{"hyperparameters_":{"eta_":0.1,"gamma_":0,"include_categorical_":false,"lambda_":0,"max_depth_":3,"min_num_samples_":200,"num_features_":20,"num_selected_features_":10,"num_threads_":0,"objective_":"CrossEntropyLoss","sampling_factor_":1,"seed_":5843,"silent_":false,"use_timestamps_":true},"initial_prediction_":-3.9558163893783362,"peripheral_names_":["EXPD"],"peripheral_schema_":[{"categoricals_":["UCC","UCC1","UCC2","UCC3","UCC4","UCC5"],"discretes_":["EXPNYR","EXPNMO"],"join_keys_":["NEWID","BASKETID"],"name_":"EXPD","numericals_":["COST"],"targets_":["TARGET"],"time_stamps_":["TIME_STAMP","TIME_STAMP_SHIFTED"]}],"placeholder_":{"join_keys_used_":[ "NEWID", "BASKETID" ],"joined_tables_":[{"join_keys_used_":[  ],"joined_tables_":[],"name_":"EXPD","other_join_keys_used_":[  ],"other_time_stamps_used_":[  ],"time_stamps_used_":[  ],"upper_time_stamps_used_":[  ]},{"join_keys_used_":[  ],"joined_tables_":[],"name_":"EXPD","other_join_keys_used_":[  ],"other_time_stamps_used_":[  ],"time_stamps_used_":[  ],"upper_time_stamps_used_":[  ]}],"name_":"EXPD","other_join_keys_used_":[ "NEWID", "BASKETID" ],"other_time_stamps_used_":[ "TIME_STAMP_SHIFTED", "TIME_STAMP" ],"time_stamps_used_":[ "TIME_STAMP", "TIME_STAMP" ],"upper_time_stamps_used_":[ "", "" ]},"population_schema_":{"categoricals_":["UCC","UCC1","UCC2","UCC3","UCC4","UCC5"],"discretes_":["EXPNYR","EXPNMO"],"join_keys_":["NEWID","BASKETID"],"name_":"EXPD_TRAINING","numericals_":["COST"],"targets_":["TARGET"],"time_stamps_":["TIME_STAMP","TIME_STAMP_SHIFTED"]},"trees_":[{"input_":{"categoricals_":["UCC","UCC1","UCC2","UCC3","UCC4","UCC5"],"discretes_":["EXPNYR","EXPNMO"],"join_keys_":["BASKETID"],"name_":"EXPD","numericals_":["COST"],"targets_":["TARGET"],"time_stamps_":["TIME_STAMP"]},"intercept_":40.45205195585845,"loss_":"AVG","output_":{"categoricals_":["UCC","UCC1","UCC2","UCC3","UCC4","UCC5"],"discretes_":["EXPNYR","EXPNMO"],"join_keys_":["BASKETID"],"name_":"EXPD","numericals_":["COST"],"targets_":["TARGET"],"time_stamps_":["TIME_STAMP"]},"peripheral_used_":1,"root_":{"categories_used_":[563,581,583,586,590,600,603,615,617,621,622,1350],"child_greater_":{"categories_used_":[496],"child_greater_":{"categories_used_":[477],"child_greater_":{"input_":{"categoricals_":["UCC","UCC1","UCC2","UCC3","UCC4","UCC5"],"discretes_":["EXPNYR","EXPNMO"],"join_keys_":["BASKETID"],"name_":"EXPD","numericals_":["COST"],"targets_":["TARGET"],"time_stamps_":["TIME_STAMP"]},"output_":{"categoricals_":["UCC","UCC1","UCC2","UCC3","UCC4","UCC5"],"discretes_":["EXPNYR","EXPNMO"],"join_keys_":["BASKETID"],"name_":"EXPD","numericals_":["COST"],"targets_":["TARGET"],"time_stamps_":["TIME_STAMP"]},"weight_":-50.53356272130764},"child_smaller_":{"categories_used_":[],"child_greater_":{"input_":{"categoricals_":["UCC","UCC1","UCC2","UCC3","UCC4","UCC5"],"discretes_":["EXPNYR","EXPNMO"],"join_keys_":["BASKETID"],"name_":"EXPD","numericals_":["COST"],"targets_":["TARGET"],"time_stamps_":["TIME_STAMP"]},"output_":{"categoricals_":["UCC","UCC1","UCC2","UCC3","UCC4","UCC5"],"discretes_":["EXPNYR","EXPNMO"],"join_keys_":["BASKETID"],"name_":"EXPD","numericals_":["COST"],"targets_":["TARGET"],"time_stamps_":["TIME_STAMP"]},"weight_":-46.71850186688365},"child_smaller_":{"input_":{"categoricals_":["UCC","UCC1","UCC2","UCC3","UCC4","UCC5"],"discretes_":["EXPNYR","EXPNMO"],"join_keys_":["BASKETID"],"name_":"EXPD","numericals_":["COST"],"targets_":["TARGET"],"time_stamps_":["TIME_STAMP"]},"output_":{"categoricals_":["UCC","UCC1","UCC2","UCC3","UCC4","UCC5"],"discretes_":["EXPNYR","EXPNMO"],"join_keys_":["BASKETID"],"name_":"EXPD","numericals_":["COST"],"targets_":["TARGET"],"time_stamps_":["TIME_STAMP"]},"weight_":-45.328094516289255},"column_":1,"column_input_":0,"critical_value_":2,"data_used_":"discrete_input","input_":{"categoricals_":["UCC","UCC1","UCC2","UCC3","UCC4","UCC5"],"discretes_":["EXPNYR","EXPNMO"],"join_keys_":["BASKETID"],"name_":"EXPD","numericals_":["COST"],"targets_":["TARGET"],"time_stamps_":["TIME_STAMP"]},"output_":{"categoricals_":["UCC","UCC1","UCC2","UCC3","UCC4","UCC5"],"discretes_":["EXPNYR","EXPNMO"],"join_keys_":["BASKETID"],"name_":"EXPD","numericals_":["COST"],"targets_":["TARGET"],"time_stamps_":["TIME_STAMP"]},"weight_":-46.32371429994854},"column_":1,"column_input_":0,"critical_value_":0,"data_used_":"categorical_input","input_":{"categoricals_":["UCC","UCC1","UCC2","UCC3","UCC4","UCC5"],"discretes_":["EXPNYR","EXPNMO"],"join_keys_":["BASKETID"],"name_":"EXPD","numericals_":["COST"],"targets_":["TARGET"],"time_stamps_":["TIME_STAMP"]},"output_":{"categoricals_":["UCC","UCC1","UCC2","UCC3","UCC4","UCC5"],"discretes_":["EXPNYR","EXPNMO"],"join_keys_":["BASKETID"],"name_":"EXPD","numericals_":["COST"],"targets_":["TARGET"],"time_stamps_":["TIME_STAMP"]},"weight_":-46.79180431000703},"child_smaller_":{"categories_used_":[],"child_greater_":{"categories_used_":[481],"child_greater_":{"input_":{"categoricals_":["UCC","UCC1","UCC2","UCC3","UCC4","UCC5"],"discretes_":["EXPNYR","EXPNMO"],"join_keys_":["BASKETID"],"name_":"EXPD","numericals_":["COST"],"targets_":["TARGET"],"time_stamps_":["TIME_STAMP"]},"output_":{"categoricals_":["UCC","UCC1","UCC2","UCC3","UCC4","UCC5"],"discretes_":["EXPNYR","EXPNMO"],"join_keys_":["BASKETID"],"name_":"EXPD","numericals_":["COST"],"targets_":["TARGET"],"time_stamps_":["TIME_STAMP"]}},"child_smaller_":{"input_":{"categoricals_":["UCC","UCC1","UCC2","UCC3","UCC4","UCC5"],"discretes_":["EXPNYR","EXPNMO"],"join_keys_":["BASKETID"],"name_":"EXPD","numericals_":["COST"],"targets_":["TARGET"],"time_stamps_":["TIME_STAMP"]},"output_":{"categoricals_":["UCC","UCC1","UCC2","UCC3","UCC4","UCC5"],"discretes_":["EXPNYR","EXPNMO"],"join_keys_":["BASKETID"],"name_":"EXPD","numericals_":["COST"],"targets_":["TARGET"],"time_stamps_":["TIME_STAMP"]},"weight_":-35.883790958112},"column_":1,"column_input_":0,"critical_value_":0,"data_used_":"categorical_output","input_":{"categoricals_":["UCC","UCC1","UCC2","UCC3","UCC4","UCC5"],"discretes_":["EXPNYR","EXPNMO"],"join_keys_":["BASKETID"],"name_":"EXPD","numericals_":["COST"],"targets_":["TARGET"],"time_stamps_":["TIME_STAMP"]},"output_":{"categoricals_":["UCC","UCC1","UCC2","UCC3","UCC4","UCC5"],"discretes_":["EXPNYR","EXPNMO"],"join_keys_":["BASKETID"],"name_":"EXPD","numericals_":["COST"],"targets_":["TARGET"],"time_stamps_":["TIME_STAMP"]}},"child_smaller_":{"input_":{"categoricals_":["UCC","UCC1","UCC2","UCC3","UCC4","UCC5"],"discretes_":["EXPNYR","EXPNMO"],"join_keys_":["BASKETID"],"name_":"EXPD","numericals_":["COST"],"targets_":["TARGET"],"time_stamps_":["TIME_STAMP"]},"output_":{"categoricals_":["UCC","UCC1","UCC2","UCC3","UCC4","UCC5"],"discretes_":["EXPNYR","EXPNMO"],"join_keys_":["BASKETID"],"name_":"EXPD","numericals_":["COST"],"targets_":["TARGET"],"time_stamps_":["TIME_STAMP"]},"weight_":-34.80731328951543},"column_":1,"column_input_":0,"critical_value_":6,"data_used_":"discrete_input","input_":{"categoricals_":["UCC","UCC1","UCC2","UCC3","UCC4","UCC5"],"discretes_":["EXPNYR","EXPNMO"],"join_keys_":["BASKETID"],"name_":"EXPD","numericals_":["COST"],"targets_":["TARGET"],"time_stamps_":["TIME_STAMP"]},"output_":{"categoricals_":["UCC","UCC1","UCC2","UCC3","UCC4","UCC5"],"discretes_":["EXPNYR","EXPNMO"],"join_keys_":["BASKETID"],"name_":"EXPD","numericals_":["COST"],"targets_":["TARGET"],"time_stamps_":["TIME_STAMP"]}},"column_":2,"column_input_":0,"critical_value_":0,"data_used_":"categorical_output","input_":{"categoricals_":["UCC","UCC1","UCC2","UCC3","UCC4","UCC5"],"discretes_":["EXPNYR","EXPNMO"],"join_keys_":["BASKETID"],"name_":"EXPD","numericals_":["COST"],"targets_":["TARGET"],"time_stamps_":["TIME_STAMP"]},"output_":{"categoricals_":["UCC","UCC1","UCC2","UCC3","UCC4","UCC5"],"discretes_":["EXPNYR","EXPNMO"],"join_keys_":["BASKETID"],"name_":"EXPD","numericals_":["COST"],"targets_":["TARGET"],"time_stamps_":["TIME_STAMP"]}},"child_smaller_":{"input_":{"categoricals_":["UCC","UCC1","UCC2","UCC3","UCC4","UCC5"],"discretes_":["EXPNYR","EXPNMO"],"join_keys_":["BASKETID"],"name_":"EXPD","numericals_":["COST"],"targets_":["TARGET"],"time_stamps_":["TIME_STAMP"]},"output_":{"categoricals_":["UCC","UCC1","UCC2","UCC3","UCC4","UCC5"],"discretes_":["EXPNYR","EXPNMO"],"join_keys_":["BASKETID"],"name_":"EXPD","numericals_":["COST"],"targets_":["TARGET"],"time_stamps_":["TIME_STAMP"]},"weight_":-41.06855179847536},"column_":3,"column_input_":0,"critical_value_":0,"data_used_":"categorical_input","input_":{"categoricals_":["UCC","UCC1","UCC2","UCC3","UCC4","UCC5"],"discretes_":["EXPNYR","EXPNMO"],"join_keys_":["BASKETID"],"name_":"EXPD","numericals_":["COST"],"targets_":["TARGET"],"time_stamps_":["TIME_STAMP"]},"output_":{"categoricals_":["UCC","UCC1","UCC2","UCC3","UCC4","UCC5"],"discretes_":["EXPNYR","EXPNMO"],"join_keys_":["BASKETID"],"name_":"EXPD","numericals_":["COST"],"targets_":["TARGET"],"time_stamps_":["TIME_STAMP"]},"weight_":0},"update_rate_":0.5105782509614556},{"input_":{"categoricals_":["UCC","UCC1","UCC2","UCC3","UCC4","UCC5"],"discretes_":["EXPNYR","EXPNMO"],"join_keys_":["BASKETID"],"name_":"EXPD","numericals_":["COST"],"targets_":["TARGET"],"time_stamps_":["TIME_STAMP"]},"intercept_":-0.2402437072018381,"loss_":"SUM","output_":{"categoricals_":["UCC","UCC1","UCC2","UCC3","UCC4","UCC5"],"discretes_":["EXPNYR","EXPNMO"],"join_keys_":["BASKETID"],"name_":"EXPD","numericals_":["COST"],"targets_":["TARGET"],"time_stamps_":["TIME_STAMP"]},"peripheral_used_":1,"root_":{"categories_used_":[1027,1035],"child_greater_":{"categories_used_":[],"child_greater_":{"input_":{"categoricals_":["UCC","UCC1","UCC2","UCC3","UCC4","UCC5"],"discretes_":["EXPNYR","EXPNMO"],"join_keys_":["BASKETID"],"name_":"EXPD","numericals_":["COST"],"targets_":["TARGET"],"time_stamps_":["TIME_STAMP"]},"output_":{"categoricals_":["UCC","UCC1","UCC2","UCC3","UCC4","UCC5"],"discretes_":["EXPNYR","EXPNMO"],"join_keys_":["BASKETID"],"name_":"EXPD","numericals_":["COST"],"targets_":["TARGET"],"time_stamps_":["TIME_STAMP"]},"weight_":0.5316600542028187},"child_smaller_":{"input_":{"categoricals_":["UCC","UCC1","UCC2","UCC3","UCC4","UCC5"],"discretes_":["EXPNYR","EXPNMO"],"join_keys_":["BASKETID"],"name_":"EXPD","numericals_":["COST"],"targets_":["TARGET"],"time_stamps_":["TIME_STAMP"]},"output_":{"categoricals_":["UCC","UCC1","UCC2","UCC3","UCC4","UCC5"],"discretes_":["EXPNYR","EXPNMO"],"join_keys_":["BASKETID"],"name_":"EXPD","numericals_":["COST"],"targets_":["TARGET"],"time_stamps_":["TIME_STAMP"]},"weight_":-0.01736695656383443},"column_":1,"column_input_":0,"critical_value_":3,"data_used_":"discrete_input","input_":{"categoricals_":["UCC","UCC1","UCC2","UCC3","UCC4","UCC5"],"discretes_":["EXPNYR","EXPNMO"],"join_keys_":["BASKETID"],"name_":"EXPD","numericals_":["COST"],"targets_":["TARGET"],"time_stamps_":["TIME_STAMP"]},"output_":{"categoricals_":["UCC","UCC1","UCC2","UCC3","UCC4","UCC5"],"discretes_":["EXPNYR","EXPNMO"],"join_keys_":["BASKETID"],"name_":"EXPD","numericals_":["COST"],"targets_":["TARGET"],"time_stamps_":["TIME_STAMP"]},"weight_":0.44859969955128837},"child_smaller_":{"categories_used_":[1392],"child_greater_":{"input_":{"categoricals_":["UCC","UCC1","UCC2","UCC3","UCC4","UCC5"],"discretes_":["EXPNYR","EXPNMO"],"join_keys_":["BASKETID"],"name_":"EXPD","numericals_":["COST"],"targets_":["TARGET"],"time_stamps_":["TIME_STAMP"]},"output_":{"categoricals_":["UCC","UCC1","UCC2","UCC3","UCC4","UCC5"],"discretes_":["EXPNYR","EXPNMO"],"join_keys_":["BASKETID"],"name_":"EXPD","numericals_":["COST"],"targets_":["TARGET"],"time_stamps_":["TIME_STAMP"]},"weight_":0.5971412585761184},"child_smaller_":{"categories_used_":[658,661,663,664,666,667,668,669,671,673,674,677,692,693,698,701,702,703,705,707,709,720,723,724,728,734,736,744,747,757,759,765,774,775,776,777,779,780,793,803,816,848,1357,1359,1361,1363,1364,1365,1367,1371,1374,1377,1380,1382,1383,1384,1386,1387],"child_greater_":{"categories_used_":[489,490,493,498,500,502,510,512,513,520,524,525,533,534,1332,1333,1334,1335,1337,1338,1340],"child_greater_":{"input_":{"categoricals_":["UCC","UCC1","UCC2","UCC3","UCC4","UCC5"],"discretes_":["EXPNYR","EXPNMO"],"join_keys_":["BASKETID"],"name_":"EXPD","numericals_":["COST"],"targets_":["TARGET"],"time_stamps_":["TIME_STAMP"]},"output_":{"categoricals_":["UCC","UCC1","UCC2","UCC3","UCC4","UCC5"],"discretes_":["EXPNYR","EXPNMO"],"join_keys_":["BASKETID"],"name_":"EXPD","numericals_":["COST"],"targets_":["TARGET"],"time_stamps_":["TIME_STAMP"]},"weight_":0.22570587841819653},"child_smaller_":{"input_":{"categoricals_":["UCC","UCC1","UCC2","UCC3","UCC4","UCC5"],"discretes_":["EXPNYR","EXPNMO"],"join_keys_":["BASKETID"],"name_":"EXPD","numericals_":["COST"],"targets_":["TARGET"],"time_stamps_":["TIME_STAMP"]},"output_":{"categoricals_":["UCC","UCC1","UCC2","UCC3","UCC4","UCC5"],"discretes_":["EXPNYR","EXPNMO"],"join_keys_":["BASKETID"],"name_":"EXPD","numericals_":["COST"],"targets_":["TARGET"],"time_stamps_":["TIME_STAMP"]},"weight_":0.0654360376694494},"column_":2,"column_input_":0,"critical_value_":0,"data_used_":"categorical_input","input_":{"categoricals_":["UCC","UCC1","UCC2","UCC3","UCC4","UCC5"],"discretes_":["EXPNYR","EXPNMO"],"join_keys_":["BASKETID"],"name_":"EXPD","numericals_":["COST"],"targets_":["TARGET"],"time_stamps_":["TIME_STAMP"]},"output_":{"categoricals_":["UCC","UCC1","UCC2","UCC3","UCC4","UCC5"],"discretes_":["EXPNYR","EXPNMO"],"join_keys_":["BASKETID"],"name_":"EXPD","numericals_":["COST"],"targets_":["TARGET"],"time_stamps_":["TIME_STAMP"]},"weight_":0.1174379548435541},"child_smaller_":{"categories_used_":[486,487,489,490,491,494,496,498,499,500,501,502,503,505,511,513,514,521,522,525,526,528,529,530,535,541,542,1333,1339,1340],"child_greater_":{"input_":{"categoricals_":["UCC","UCC1","UCC2","UCC3","UCC4","UCC5"],"discretes_":["EXPNYR","EXPNMO"],"join_keys_":["BASKETID"],"name_":"EXPD","numericals_":["COST"],"targets_":["TARGET"],"time_stamps_":["TIME_STAMP"]},"output_":{"categoricals_":["UCC","UCC1","UCC2","UCC3","UCC4","UCC5"],"discretes_":["EXPNYR","EXPNMO"],"join_keys_":["BASKETID"],"name_":"EXPD","numericals_":["COST"],"targets_":["TARGET"],"time_stamps_":["TIME_STAMP"]},"weight_":-0.05484816449520587},"child_smaller_":{"input_":{"categoricals_":["UCC","UCC1","UCC2","UCC3","UCC4","UCC5"],"discretes_":["EXPNYR","EXPNMO"],"join_keys_":["BASKETID"],"name_":"EXPD","numericals_":["COST"],"targets_":["TARGET"],"time_stamps_":["TIME_STAMP"]},"output_":{"categoricals_":["UCC","UCC1","UCC2","UCC3","UCC4","UCC5"],"discretes_":["EXPNYR","EXPNMO"],"join_keys_":["BASKETID"],"name_":"EXPD","numericals_":["COST"],"targets_":["TARGET"],"time_stamps_":["TIME_STAMP"]},"weight_":-0.20037782635408335},"column_":2,"column_input_":0,"critical_value_":0,"data_used_":"categorical_input","input_":{"categoricals_":["UCC","UCC1","UCC2","UCC3","UCC4","UCC5"],"discretes_":["EXPNYR","EXPNMO"],"join_keys_":["BASKETID"],"name_":"EXPD","numericals_":["COST"],"targets_":["TARGET"],"time_stamps_":["TIME_STAMP"]},"output_":{"categoricals_":["UCC","UCC1","UCC2","UCC3","UCC4","UCC5"],"discretes_":["EXPNYR","EXPNMO"],"join_keys_":["BASKETID"],"name_":"EXPD","numericals_":["COST"],"targets_":["TARGET"],"time_stamps_":["TIME_STAMP"]},"weight_":-0.0897356108425796},"column_":4,"column_input_":0,"critical_value_":0,"data_used_":"categorical_input","input_":{"categoricals_":["UCC","UCC1","UCC2","UCC3","UCC4","UCC5"],"discretes_":["EXPNYR","EXPNMO"],"join_keys_":["BASKETID"],"name_":"EXPD","numericals_":["COST"],"targets_":["TARGET"],"time_stamps_":["TIME_STAMP"]},"output_":{"categoricals_":["UCC","UCC1","UCC2","UCC3","UCC4","UCC5"],"discretes_":["EXPNYR","EXPNMO"],"join_keys_":["BASKETID"],"name_":"EXPD","numericals_":["COST"],"targets_":["TARGET"],"time_stamps_":["TIME_STAMP"]},"weight_":0.0026779298183280944},"column_":4,"column_input_":0,"critical_value_":0,"data_used_":"categorical_output","input_":{"categoricals_":["UCC","UCC1","UCC2","UCC3","UCC4","UCC5"],"discretes_":["EXPNYR","EXPNMO"],"join_keys_":["BASKETID"],"name_":"EXPD","numericals_":["COST"],"targets_":["TARGET"],"time_stamps_":["TIME_STAMP"]},"output_":{"categoricals_":["UCC","UCC1","UCC2","UCC3","UCC4","UCC5"],"discretes_":["EXPNYR","EXPNMO"],"join_keys_":["BASKETID"],"name_":"EXPD","numericals_":["COST"],"targets_":["TARGET"],"time_stamps_":["TIME_STAMP"]},"weight_":0.003308509498521067},"column_":5,"column_input_":0,"critical_value_":0,"data_used_":"categorical_output","input_":{"categoricals_":["UCC","UCC1","UCC2","UCC3","UCC4","UCC5"],"discretes_":["EXPNYR","EXPNMO"],"join_keys_":["BASKETID"],"name_":"EXPD","numericals_":["COST"],"targets_":["TARGET"],"time_stamps_":["TIME_STAMP"]},"output_":{"categoricals_":["UCC","UCC1","UCC2","UCC3","UCC4","UCC5"],"discretes_":["EXPNYR","EXPNMO"],"join_keys_":["BASKETID"],"name_":"EXPD","numericals_":["COST"],"targets_":["TARGET"],"time_stamps_":["TIME_STAMP"]},"weight_":0},"update_rate_":0.3499318808345731},{"input_":{"categoricals_":["UCC","UCC1","UCC2","UCC3","UCC4","UCC5"],"discretes_":["EXPNYR","EXPNMO"],"join_keys_":["BASKETID"],"name_":"EXPD","numericals_":["COST"],"targets_":["TARGET"],"time_stamps_":["TIME_STAMP"]},"intercept_":-0.24574636352344784,"loss_":"SUM","output_":{"categoricals_":["UCC","UCC1","UCC2","UCC3","UCC4","UCC5"],"discretes_":["EXPNYR","EXPNMO"],"join_keys_":["BASKETID"],"name_":"EXPD","numericals_":["COST"],"targets_":["TARGET"],"time_stamps_":["TIME_STAMP"]},"peripheral_used_":1,"root_":{"categories_used_":[542],"child_greater_":{"input_":{"categoricals_":["UCC","UCC1","UCC2","UCC3","UCC4","UCC5"],"discretes_":["EXPNYR","EXPNMO"],"join_keys_":["BASKETID"],"name_":"EXPD","numericals_":["COST"],"targets_":["TARGET"],"time_stamps_":["TIME_STAMP"]},"output_":{"categoricals_":["UCC","UCC1","UCC2","UCC3","UCC4","UCC5"],"discretes_":["EXPNYR","EXPNMO"],"join_keys_":["BASKETID"],"name_":"EXPD","numericals_":["COST"],"targets_":["TARGET"],"time_stamps_":["TIME_STAMP"]},"weight_":0.32827704076509545},"child_smaller_":{"categories_used_":[660,661,662,664,665,666,668,669,671,673,674,676,677,678,679,692,697,698,699,703,705,706,707,708,709,710,711,717,720,724,727,728,734,736,741,744,746,747,756,757,759,763,768,770,777,778,779,780,786,788,803,811,812,816,819,822,830,832,841,848,1358,1360,1361,1362,1364,1366,1369,1371,1372,1380,1381,1383,1392],"child_greater_":{"categories_used_":[916,917,919,922,927,931,932,934,937,938,943,944,945,946,953,955,958,965,971,972,974,976,987,989,990,993,996,1006,1008,1022,1025,1028,1050,1059,1060,1064,1066,1120,1406,1408,1409,1410,1412,1415,1419,1422,1423,1431,1432,1434],"child_greater_":{"categories_used_":[5,6,8,9,10,15,16,17,19,20,21,25,26,28,30,44,48,50,53,55,56,61,62,64,65,66,73,74,79,82,90,97,110,123,148,191,1272,1274,1275,1278,1279,1280,1281,1286,1288,1297],"child_greater_":{"input_":{"categoricals_":["UCC","UCC1","UCC2","UCC3","UCC4","UCC5"],"discretes_":["EXPNYR","EXPNMO"],"join_keys_":["BASKETID"],"name_":"EXPD","numericals_":["COST"],"targets_":["TARGET"],"time_stamps_":["TIME_STAMP"]},"output_":{"categoricals_":["UCC","UCC1","UCC2","UCC3","UCC4","UCC5"],"discretes_":["EXPNYR","EXPNMO"],"join_keys_":["BASKETID"],"name_":"EXPD","numericals_":["COST"],"targets_":["TARGET"],"time_stamps_":["TIME_STAMP"]},"weight_":0.13554493383783583},"child_smaller_":{"input_":{"categoricals_":["UCC","UCC1","UCC2","UCC3","UCC4","UCC5"],"discretes_":["EXPNYR","EXPNMO"],"join_keys_":["BASKETID"],"name_":"EXPD","numericals_":["COST"],"targets_":["TARGET"],"time_stamps_":["TIME_STAMP"]},"output_":{"categoricals_":["UCC","UCC1","UCC2","UCC3","UCC4","UCC5"],"discretes_":["EXPNYR","EXPNMO"],"join_keys_":["BASKETID"],"name_":"EXPD","numericals_":["COST"],"targets_":["TARGET"],"time_stamps_":["TIME_STAMP"]},"weight_":0.17127549315278706},"column_":0,"column_input_":0,"critical_value_":0,"data_used_":"categorical_output","input_":{"categoricals_":["UCC","UCC1","UCC2","UCC3","UCC4","UCC5"],"discretes_":["EXPNYR","EXPNMO"],"join_keys_":["BASKETID"],"name_":"EXPD","numericals_":["COST"],"targets_":["TARGET"],"time_stamps_":["TIME_STAMP"]},"output_":{"categoricals_":["UCC","UCC1","UCC2","UCC3","UCC4","UCC5"],"discretes_":["EXPNYR","EXPNMO"],"join_keys_":["BASKETID"],"name_":"EXPD","numericals_":["COST"],"targets_":["TARGET"],"time_stamps_":["TIME_STAMP"]},"weight_":0.1488688461578493},"child_smaller_":{"categories_used_":[655,656,664,665,666,667,668,669,673,674,692,696,700,701,702,703,708,709,720,722,745,757,832,1355,1361,1363,1373],"child_greater_":{"input_":{"categoricals_":["UCC","UCC1","UCC2","UCC3","UCC4","UCC5"],"discretes_":["EXPNYR","EXPNMO"],"join_keys_":["BASKETID"],"name_":"EXPD","numericals_":["COST"],"targets_":["TARGET"],"time_stamps_":["TIME_STAMP"]},"output_":{"categoricals_":["UCC","UCC1","UCC2","UCC3","UCC4","UCC5"],"discretes_":["EXPNYR","EXPNMO"],"join_keys_":["BASKETID"],"name_":"EXPD","numericals_":["COST"],"targets_":["TARGET"],"time_stamps_":["TIME_STAMP"]},"weight_":0.004783348807164282},"child_smaller_":{"input_":{"categoricals_":["UCC","UCC1","UCC2","UCC3","UCC4","UCC5"],"discretes_":["EXPNYR","EXPNMO"],"join_keys_":["BASKETID"],"name_":"EXPD","numericals_":["COST"],"targets_":["TARGET"],"time_stamps_":["TIME_STAMP"]},"output_":{"categoricals_":["UCC","UCC1","UCC2","UCC3","UCC4","UCC5"],"discretes_":["EXPNYR","EXPNMO"],"join_keys_":["BASKETID"],"name_":"EXPD","numericals_":["COST"],"targets_":["TARGET"],"time_stamps_":["TIME_STAMP"]},"weight_":-0.04387930493127712},"column_":4,"column_input_":0,"critical_value_":0,"data_used_":"categorical_output","input_":{"categoricals_":["UCC","UCC1","UCC2","UCC3","UCC4","UCC5"],"discretes_":["EXPNYR","EXPNMO"],"join_keys_":["BASKETID"],"name_":"EXPD","numericals_":["COST"],"targets_":["TARGET"],"time_stamps_":["TIME_STAMP"]},"output_":{"categoricals_":["UCC","UCC1","UCC2","UCC3","UCC4","UCC5"],"discretes_":["EXPNYR","EXPNMO"],"join_keys_":["BASKETID"],"name_":"EXPD","numericals_":["COST"],"targets_":["TARGET"],"time_stamps_":["TIME_STAMP"]},"weight_":-0.017155118491778937},"column_":5,"column_input_":0,"critical_value_":0,"data_used_":"categorical_input","input_":{"categoricals_":["UCC","UCC1","UCC2","UCC3","UCC4","UCC5"],"discretes_":["EXPNYR","EXPNMO"],"join_keys_":["BASKETID"],"name_":"EXPD","numericals_":["COST"],"targets_":["TARGET"],"time_stamps_":["TIME_STAMP"]},"output_":{"categoricals_":["UCC","UCC1","UCC2","UCC3","UCC4","UCC5"],"discretes_":["EXPNYR","EXPNMO"],"join_keys_":["BASKETID"],"name_":"EXPD","numericals_":["COST"],"targets_":["TARGET"],"time_stamps_":["TIME_STAMP"]},"weight_":0.06713037855366678},"child_smaller_":{"categories_used_":[489,490,501,505,514,516,521,528,529,1338,1340],"child_greater_":{"categories_used_":[482,484,1330],"child_greater_":{"input_":{"categoricals_":["UCC","UCC1","UCC2","UCC3","UCC4","UCC5"],"discretes_":["EXPNYR","EXPNMO"],"join_keys_":["BASKETID"],"name_":"EXPD","numericals_":["COST"],"targets_":["TARGET"],"time_stamps_":["TIME_STAMP"]},"output_":{"categoricals_":["UCC","UCC1","UCC2","UCC3","UCC4","UCC5"],"discretes_":["EXPNYR","EXPNMO"],"join_keys_":["BASKETID"],"name_":"EXPD","numericals_":["COST"],"targets_":["TARGET"],"time_stamps_":["TIME_STAMP"]},"weight_":0.2390441864521667},"child_smaller_":{"input_":{"categoricals_":["UCC","UCC1","UCC2","UCC3","UCC4","UCC5"],"discretes_":["EXPNYR","EXPNMO"],"join_keys_":["BASKETID"],"name_":"EXPD","numericals_":["COST"],"targets_":["TARGET"],"time_stamps_":["TIME_STAMP"]},"output_":{"categoricals_":["UCC","UCC1","UCC2","UCC3","UCC4","UCC5"],"discretes_":["EXPNYR","EXPNMO"],"join_keys_":["BASKETID"],"name_":"EXPD","numericals_":["COST"],"targets_":["TARGET"],"time_stamps_":["TIME_STAMP"]},"weight_":-0.055178855001512594},"column_":1,"column_input_":0,"critical_value_":0,"data_used_":"categorical_input","input_":{"categoricals_":["UCC","UCC1","UCC2","UCC3","UCC4","UCC5"],"discretes_":["EXPNYR","EXPNMO"],"join_keys_":["BASKETID"],"name_":"EXPD","numericals_":["COST"],"targets_":["TARGET"],"time_stamps_":["TIME_STAMP"]},"output_":{"categoricals_":["UCC","UCC1","UCC2","UCC3","UCC4","UCC5"],"discretes_":["EXPNYR","EXPNMO"],"join_keys_":["BASKETID"],"name_":"EXPD","numericals_":["COST"],"targets_":["TARGET"],"time_stamps_":["TIME_STAMP"]},"weight_":-0.02752315539598126},"child_smaller_":{"categories_used_":[19,54,56,84,97,99,103,133,146,147,160,191,1274,1286,1304,1313],"child_greater_":{"input_":{"categoricals_":["UCC","UCC1","UCC2","UCC3","UCC4","UCC5"],"discretes_":["EXPNYR","EXPNMO"],"join_keys_":["BASKETID"],"name_":"EXPD","numericals_":["COST"],"targets_":["TARGET"],"time_stamps_":["TIME_STAMP"]},"output_":{"categoricals_":["UCC","UCC1","UCC2","UCC3","UCC4","UCC5"],"discretes_":["EXPNYR","EXPNMO"],"join_keys_":["BASKETID"],"name_":"EXPD","numericals_":["COST"],"targets_":["TARGET"],"time_stamps_":["TIME_STAMP"]},"weight_":-0.025711782500059885},"child_smaller_":{"input_":{"categoricals_":["UCC","UCC1","UCC2","UCC3","UCC4","UCC5"],"discretes_":["EXPNYR","EXPNMO"],"join_keys_":["BASKETID"],"name_":"EXPD","numericals_":["COST"],"targets_":["TARGET"],"time_stamps_":["TIME_STAMP"]},"output_":{"categoricals_":["UCC","UCC1","UCC2","UCC3","UCC4","UCC5"],"discretes_":["EXPNYR","EXPNMO"],"join_keys_":["BASKETID"],"name_":"EXPD","numericals_":["COST"],"targets_":["TARGET"],"time_stamps_":["TIME_STAMP"]},"weight_":-0.18356090124502988},"column_":0,"column_input_":0,"critical_value_":0,"data_used_":"categorical_input","input_":{"categoricals_":["UCC","UCC1","UCC2","UCC3","UCC4","UCC5"],"discretes_":["EXPNYR","EXPNMO"],"join_keys_":["BASKETID"],"name_":"EXPD","numericals_":["COST"],"targets_":["TARGET"],"time_stamps_":["TIME_STAMP"]},"output_":{"categoricals_":["UCC","UCC1","UCC2","UCC3","UCC4","UCC5"],"discretes_":["EXPNYR","EXPNMO"],"join_keys_":["BASKETID"],"name_":"EXPD","numericals_":["COST"],"targets_":["TARGET"],"time_stamps_":["TIME_STAMP"]},"weight_":-0.1353095617397863},"column_":2,"column_input_":0,"critical_value_":0,"data_used_":"categorical_input","input_":{"categoricals_":["UCC","UCC1","UCC2","UCC3","UCC4","UCC5"],"discretes_":["EXPNYR","EXPNMO"],"join_keys_":["BASKETID"],"name_":"EXPD","numericals_":["COST"],"targets_":["TARGET"],"time_stamps_":["TIME_STAMP"]},"output_":{"categoricals_":["UCC","UCC1","UCC2","UCC3","UCC4","UCC5"],"discretes_":["EXPNYR","EXPNMO"],"join_keys_":["BASKETID"],"name_":"EXPD","numericals_":["COST"],"targets_":["TARGET"],"time_stamps_":["TIME_STAMP"]},"weight_":-0.08571012551453219},"column_":4,"column_input_":0,"critical_value_":0,"data_used_":"categorical_input","input_":{"categoricals_":["UCC","UCC1","UCC2","UCC3","UCC4","UCC5"],"discretes_":["EXPNYR","EXPNMO"],"join_keys_":["BASKETID"],"name_":"EXPD","numericals_":["COST"],"targets_":["TARGET"],"time_stamps_":["TIME_STAMP"]},"output_":{"categoricals_":["UCC","UCC1","UCC2","UCC3","UCC4","UCC5"],"discretes_":["EXPNYR","EXPNMO"],"join_keys_":["BASKETID"],"name_":"EXPD","numericals_":["COST"],"targets_":["TARGET"],"time_stamps_":["TIME_STAMP"]},"weight_":0.0011353561511729887},"column_":2,"column_input_":0,"critical_value_":0,"data_used_":"categorical_output","input_":{"categoricals_":["UCC","UCC1","UCC2","UCC3","UCC4","UCC5"],"discretes_":["EXPNYR","EXPNMO"],"join_keys_":["BASKETID"],"name_":"EXPD","numericals_":["COST"],"targets_":["TARGET"],"time_stamps_":["TIME_STAMP"]},"output_":{"categoricals_":["UCC","UCC1","UCC2","UCC3","UCC4","UCC5"],"discretes_":["EXPNYR","EXPNMO"],"join_keys_":["BASKETID"],"name_":"EXPD","numericals_":["COST"],"targets_":["TARGET"],"time_stamps_":["TIME_STAMP"]},"weight_":0},"update_rate_":0.543958476620834},{"input_":{"categoricals_":["UCC","UCC1","UCC2","UCC3","UCC4","UCC5"],"discretes_":["EXPNYR","EXPNMO"],"join_keys_":["BASKETID"],"name_":"EXPD","numericals_":["COST"],"targets_":["TARGET"],"time_stamps_":["TIME_STAMP"]},"intercept_":-0.950228492121404,"loss_":"AVG","output_":{"categoricals_":["UCC","UCC1","UCC2","UCC3","UCC4","UCC5"],"discretes_":["EXPNYR","EXPNMO"],"join_keys_":["BASKETID"],"name_":"EXPD","numericals_":["COST"],"targets_":["TARGET"],"time_stamps_":["TIME_STAMP"]},"peripheral_used_":1,"root_":{"categories_used_":[486,489,492,494,495,498,499,500,501,502,503,504,508,510,516,518,521,522,526,528,530,535,537,1333,1334,1337,1340],"child_greater_":{"categories_used_":[1335],"child_greater_":{"input_":{"categoricals_":["UCC","UCC1","UCC2","UCC3","UCC4","UCC5"],"discretes_":["EXPNYR","EXPNMO"],"join_keys_":["BASKETID"],"name_":"EXPD","numericals_":["COST"],"targets_":["TARGET"],"time_stamps_":["TIME_STAMP"]},"output_":{"categoricals_":["UCC","UCC1","UCC2","UCC3","UCC4","UCC5"],"discretes_":["EXPNYR","EXPNMO"],"join_keys_":["BASKETID"],"name_":"EXPD","numericals_":["COST"],"targets_":["TARGET"],"time_stamps_":["TIME_STAMP"]},"weight_":-33.42594926549621},"child_smaller_":{"categories_used_":[123],"child_greater_":{"input_":{"categoricals_":["UCC","UCC1","UCC2","UCC3","UCC4","UCC5"],"discretes_":["EXPNYR","EXPNMO"],"join_keys_":["BASKETID"],"name_":"EXPD","numericals_":["COST"],"targets_":["TARGET"],"time_stamps_":["TIME_STAMP"]},"output_":{"categoricals_":["UCC","UCC1","UCC2","UCC3","UCC4","UCC5"],"discretes_":["EXPNYR","EXPNMO"],"join_keys_":["BASKETID"],"name_":"EXPD","numericals_":["COST"],"targets_":["TARGET"],"time_stamps_":["TIME_STAMP"]},"weight_":-5.8585392709591995},"child_smaller_":{"categories_used_":[530],"child_greater_":{"input_":{"categoricals_":["UCC","UCC1","UCC2","UCC3","UCC4","UCC5"],"discretes_":["EXPNYR","EXPNMO"],"join_keys_":["BASKETID"],"name_":"EXPD","numericals_":["COST"],"targets_":["TARGET"],"time_stamps_":["TIME_STAMP"]},"output_":{"categoricals_":["UCC","UCC1","UCC2","UCC3","UCC4","UCC5"],"discretes_":["EXPNYR","EXPNMO"],"join_keys_":["BASKETID"],"name_":"EXPD","numericals_":["COST"],"targets_":["TARGET"],"time_stamps_":["TIME_STAMP"]},"weight_":-37.38117676538997},"child_smaller_":{"input_":{"categoricals_":["UCC","UCC1","UCC2","UCC3","UCC4","UCC5"],"discretes_":["EXPNYR","EXPNMO"],"join_keys_":["BASKETID"],"name_":"EXPD","numericals_":["COST"],"targets_":["TARGET"],"time_stamps_":["TIME_STAMP"]},"output_":{"categoricals_":["UCC","UCC1","UCC2","UCC3","UCC4","UCC5"],"discretes_":["EXPNYR","EXPNMO"],"join_keys_":["BASKETID"],"name_":"EXPD","numericals_":["COST"],"targets_":["TARGET"],"time_stamps_":["TIME_STAMP"]},"weight_":2.6350646630478747},"column_":2,"column_input_":0,"critical_value_":0,"data_used_":"categorical_input","input_":{"categoricals_":["UCC","UCC1","UCC2","UCC3","UCC4","UCC5"],"discretes_":["EXPNYR","EXPNMO"],"join_keys_":["BASKETID"],"name_":"EXPD","numericals_":["COST"],"targets_":["TARGET"],"time_stamps_":["TIME_STAMP"]},"output_":{"categoricals_":["UCC","UCC1","UCC2","UCC3","UCC4","UCC5"],"discretes_":["EXPNYR","EXPNMO"],"join_keys_":["BASKETID"],"name_":"EXPD","numericals_":["COST"],"targets_":["TARGET"],"time_stamps_":["TIME_STAMP"]},"weight_":2.503980514444391},"column_":0,"column_input_":0,"critical_value_":0,"data_used_":"categorical_input","input_":{"categoricals_":["UCC","UCC1","UCC2","UCC3","UCC4","UCC5"],"discretes_":["EXPNYR","EXPNMO"],"join_keys_":["BASKETID"],"name_":"EXPD","numericals_":["COST"],"targets_":["TARGET"],"time_stamps_":["TIME_STAMP"]},"output_":{"categoricals_":["UCC","UCC1","UCC2","UCC3","UCC4","UCC5"],"discretes_":["EXPNYR","EXPNMO"],"join_keys_":["BASKETID"],"name_":"EXPD","numericals_":["COST"],"targets_":["TARGET"],"time_stamps_":["TIME_STAMP"]},"weight_":2.472867491587228},"column_":2,"column_input_":0,"critical_value_":0,"data_used_":"categorical_input","input_":{"categoricals_":["UCC","UCC1","UCC2","UCC3","UCC4","UCC5"],"discretes_":["EXPNYR","EXPNMO"],"join_keys_":["BASKETID"],"name_":"EXPD","numericals_":["COST"],"targets_":["TARGET"],"time_stamps_":["TIME_STAMP"]},"output_":{"categoricals_":["UCC","UCC1","UCC2","UCC3","UCC4","UCC5"],"discretes_":["EXPNYR","EXPNMO"],"join_keys_":["BASKETID"],"name_":"EXPD","numericals_":["COST"],"targets_":["TARGET"],"time_stamps_":["TIME_STAMP"]},"weight_":2.0018830400026397},"child_smaller_":{"categories_used_":[484],"child_greater_":{"categories_used_":[477],"child_greater_":{"input_":{"categoricals_":["UCC","UCC1","UCC2","UCC3","UCC4","UCC5"],"discretes_":["EXPNYR","EXPNMO"],"join_keys_":["BASKETID"],"name_":"EXPD","numericals_":["COST"],"targets_":["TARGET"],"time_stamps_":["TIME_STAMP"]},"output_":{"categoricals_":["UCC","UCC1","UCC2","UCC3","UCC4","UCC5"],"discretes_":["EXPNYR","EXPNMO"],"join_keys_":["BASKETID"],"name_":"EXPD","numericals_":["COST"],"targets_":["TARGET"],"time_stamps_":["TIME_STAMP"]},"weight_":2.1299656935501243},"child_smaller_":{"input_":{"categoricals_":["UCC","UCC1","UCC2","UCC3","UCC4","UCC5"],"discretes_":["EXPNYR","EXPNMO"],"join_keys_":["BASKETID"],"name_":"EXPD","numericals_":["COST"],"targets_":["TARGET"],"time_stamps_":["TIME_STAMP"]},"output_":{"categoricals_":["UCC","UCC1","UCC2","UCC3","UCC4","UCC5"],"discretes_":["EXPNYR","EXPNMO"],"join_keys_":["BASKETID"],"name_":"EXPD","numericals_":["COST"],"targets_":["TARGET"],"time_stamps_":["TIME_STAMP"]}},"column_":1,"column_input_":0,"critical_value_":0,"data_used_":"categorical_input","input_":{"categoricals_":["UCC","UCC1","UCC2","UCC3","UCC4","UCC5"],"discretes_":["EXPNYR","EXPNMO"],"join_keys_":["BASKETID"],"name_":"EXPD","numericals_":["COST"],"targets_":["TARGET"],"time_stamps_":["TIME_STAMP"]},"output_":{"categoricals_":["UCC","UCC1","UCC2","UCC3","UCC4","UCC5"],"discretes_":["EXPNYR","EXPNMO"],"join_keys_":["BASKETID"],"name_":"EXPD","numericals_":["COST"],"targets_":["TARGET"],"time_stamps_":["TIME_STAMP"]},"weight_":2.1299656935501243},"child_smaller_":{"categories_used_":[],"child_greater_":{"categories_used_":[],"child_greater_":{"input_":{"categoricals_":["UCC","UCC1","UCC2","UCC3","UCC4","UCC5"],"discretes_":["EXPNYR","EXPNMO"],"join_keys_":["BASKETID"],"name_":"EXPD","numericals_":["COST"],"targets_":["TARGET"],"time_stamps_":["TIME_STAMP"]},"output_":{"categoricals_":["UCC","UCC1","UCC2","UCC3","UCC4","UCC5"],"discretes_":["EXPNYR","EXPNMO"],"join_keys_":["BASKETID"],"name_":"EXPD","numericals_":["COST"],"targets_":["TARGET"],"time_stamps_":["TIME_STAMP"]}},"child_smaller_":{"input_":{"categoricals_":["UCC","UCC1","UCC2","UCC3","UCC4","UCC5"],"discretes_":["EXPNYR","EXPNMO"],"join_keys_":["BASKETID"],"name_":"EXPD","numericals_":["COST"],"targets_":["TARGET"],"time_stamps_":["TIME_STAMP"]},"output_":{"categoricals_":["UCC","UCC1","UCC2","UCC3","UCC4","UCC5"],"discretes_":["EXPNYR","EXPNMO"],"join_keys_":["BASKETID"],"name_":"EXPD","numericals_":["COST"],"targets_":["TARGET"],"time_stamps_":["TIME_STAMP"]},"weight_":0},"column_":1,"column_input_":0,"critical_value_":0,"data_used_":"discrete_input_is_nan","input_":{"categoricals_":["UCC","UCC1","UCC2","UCC3","UCC4","UCC5"],"discretes_":["EXPNYR","EXPNMO"],"join_keys_":["BASKETID"],"name_":"EXPD","numericals_":["COST"],"targets_":["TARGET"],"time_stamps_":["TIME_STAMP"]},"output_":{"categoricals_":["UCC","UCC1","UCC2","UCC3","UCC4","UCC5"],"discretes_":["EXPNYR","EXPNMO"],"join_keys_":["BASKETID"],"name_":"EXPD","numericals_":["COST"],"targets_":["TARGET"],"time_stamps_":["TIME_STAMP"]}},"child_smaller_":{"input_":{"categoricals_":["UCC","UCC1","UCC2","UCC3","UCC4","UCC5"],"discretes_":["EXPNYR","EXPNMO"],"join_keys_":["BASKETID"],"name_":"EXPD","numericals_":["COST"],"targets_":["TARGET"],"time_stamps_":["TIME_STAMP"]},"output_":{"categoricals_":["UCC","UCC1","UCC2","UCC3","UCC4","UCC5"],"discretes_":["EXPNYR","EXPNMO"],"join_keys_":["BASKETID"],"name_":"EXPD","numericals_":["COST"],"targets_":["TARGET"],"time_stamps_":["TIME_STAMP"]},"weight_":0},"column_":1,"column_input_":0,"critical_value_":0,"data_used_":"discrete_input_is_nan","input_":{"categoricals_":["UCC","UCC1","UCC2","UCC3","UCC4","UCC5"],"discretes_":["EXPNYR","EXPNMO"],"join_keys_":["BASKETID"],"name_":"EXPD","numericals_":["COST"],"targets_":["TARGET"],"time_stamps_":["TIME_STAMP"]},"output_":{"categoricals_":["UCC","UCC1","UCC2","UCC3","UCC4","UCC5"],"discretes_":["EXPNYR","EXPNMO"],"join_keys_":["BASKETID"],"name_":"EXPD","numericals_":["COST"],"targets_":["TARGET"],"time_stamps_":["TIME_STAMP"]}},"column_":1,"column_input_":0,"critical_value_":0,"data_used_":"categorical_output","input_":{"categoricals_":["UCC","UCC1","UCC2","UCC3","UCC4","UCC5"],"discretes_":["EXPNYR","EXPNMO"],"join_keys_":["BASKETID"],"name_":"EXPD","numericals_":["COST"],"targets_":["TARGET"],"time_stamps_":["TIME_STAMP"]},"output_":{"categoricals_":["UCC","UCC1","UCC2","UCC3","UCC4","UCC5"],"discretes_":["EXPNYR","EXPNMO"],"join_keys_":["BASKETID"],"name_":"EXPD","numericals_":["COST"],"targets_":["TARGET"],"time_stamps_":["TIME_STAMP"]}},"column_":2,"column_input_":0,"critical_value_":0,"data_used_":"categorical_output","input_":{"categoricals_":["UCC","UCC1","UCC2","UCC3","UCC4","UCC5"],"discretes_":["EXPNYR","EXPNMO"],"join_keys_":["BASKETID"],"name_":"EXPD","numericals_":["COST"],"targets_":["TARGET"],"time_stamps_":["TIME_STAMP"]},"output_":{"categoricals_":["UCC","UCC1","UCC2","UCC3","UCC4","UCC5"],"discretes_":["EXPNYR","EXPNMO"],"join_keys_":["BASKETID"],"name_":"EXPD","numericals_":["COST"],"targets_":["TARGET"],"time_stamps_":["TIME_STAMP"]},"weight_":0},"update_rate_":0.2947355484556038},{"input_":{"categoricals_":["UCC","UCC1","UCC2","UCC3","UCC4","UCC5"],"discretes_":["EXPNYR","EXPNMO"],"join_keys_":["BASKETID"],"name_":"EXPD","numericals_":["COST"],"targets_":["TARGET"],"time_stamps_":["TIME_STAMP"]},"intercept_":-0.46427544195076653,"loss_":"SUM","output_":{"categoricals_":["UCC","UCC1","UCC2","UCC3","UCC4","UCC5"],"discretes_":["EXPNYR","EXPNMO"],"join_keys_":["BASKETID"],"name_":"EXPD","numericals_":["COST"],"targets_":["TARGET"],"time_stamps_":["TIME_STAMP"]},"peripheral_used_":1,"root_":{"categories_used_":[589],"child_greater_":{"input_":{"categoricals_":["UCC","UCC1","UCC2","UCC3","UCC4","UCC5"],"discretes_":["EXPNYR","EXPNMO"],"join_keys_":["BASKETID"],"name_":"EXPD","numericals_":["COST"],"targets_":["TARGET"],"time_stamps_":["TIME_STAMP"]},"output_":{"categoricals_":["UCC","UCC1","UCC2","UCC3","UCC4","UCC5"],"discretes_":["EXPNYR","EXPNMO"],"join_keys_":["BASKETID"],"name_":"EXPD","numericals_":["COST"],"targets_":["TARGET"],"time_stamps_":["TIME_STAMP"]},"weight_":0.8231292622996931},"child_smaller_":{"categories_used_":[210],"child_greater_":{"input_":{"categoricals_":["UCC","UCC1","UCC2","UCC3","UCC4","UCC5"],"discretes_":["EXPNYR","EXPNMO"],"join_keys_":["BASKETID"],"name_":"EXPD","numericals_":["COST"],"targets_":["TARGET"],"time_stamps_":["TIME_STAMP"]},"output_":{"categoricals_":["UCC","UCC1","UCC2","UCC3","UCC4","UCC5"],"discretes_":["EXPNYR","EXPNMO"],"join_keys_":["BASKETID"],"name_":"EXPD","numericals_":["COST"],"targets_":["TARGET"],"time_stamps_":["TIME_STAMP"]},"weight_":0.21897551485099548},"child_smaller_":{"categories_used_":[554,555,558,560,563,564,565,567,568,569,580,581,582,586,590,591,604,614,617,618,621,622,628,633,637,638,1342,1343,1347,1348,1350],"child_greater_":{"categories_used_":[],"child_greater_":{"input_":{"categoricals_":["UCC","UCC1","UCC2","UCC3","UCC4","UCC5"],"discretes_":["EXPNYR","EXPNMO"],"join_keys_":["BASKETID"],"name_":"EXPD","numericals_":["COST"],"targets_":["TARGET"],"time_stamps_":["TIME_STAMP"]},"output_":{"categoricals_":["UCC","UCC1","UCC2","UCC3","UCC4","UCC5"],"discretes_":["EXPNYR","EXPNMO"],"join_keys_":["BASKETID"],"name_":"EXPD","numericals_":["COST"],"targets_":["TARGET"],"time_stamps_":["TIME_STAMP"]},"weight_":0.09482043685955643},"child_smaller_":{"input_":{"categoricals_":["UCC","UCC1","UCC2","UCC3","UCC4","UCC5"],"discretes_":["EXPNYR","EXPNMO"],"join_keys_":["BASKETID"],"name_":"EXPD","numericals_":["COST"],"targets_":["TARGET"],"time_stamps_":["TIME_STAMP"]},"output_":{"categoricals_":["UCC","UCC1","UCC2","UCC3","UCC4","UCC5"],"discretes_":["EXPNYR","EXPNMO"],"join_keys_":["BASKETID"],"name_":"EXPD","numericals_":["COST"],"targets_":["TARGET"],"time_stamps_":["TIME_STAMP"]},"weight_":0.0159662930154997},"column_":0,"column_input_":0,"critical_value_":0,"data_used_":"same_units_categorical","input_":{"categoricals_":["UCC","UCC1","UCC2","UCC3","UCC4","UCC5"],"discretes_":["EXPNYR","EXPNMO"],"join_keys_":["BASKETID"],"name_":"EXPD","numericals_":["COST"],"targets_":["TARGET"],"time_stamps_":["TIME_STAMP"]},"output_":{"categoricals_":["UCC","UCC1","UCC2","UCC3","UCC4","UCC5"],"discretes_":["EXPNYR","EXPNMO"],"join_keys_":["BASKETID"],"name_":"EXPD","numericals_":["COST"],"targets_":["TARGET"],"time_stamps_":["TIME_STAMP"]},"weight_":0.018044982767415545},"child_smaller_":{"categories_used_":[],"child_greater_":{"input_":{"categoricals_":["UCC","UCC1","UCC2","UCC3","UCC4","UCC5"],"discretes_":["EXPNYR","EXPNMO"],"join_keys_":["BASKETID"],"name_":"EXPD","numericals_":["COST"],"targets_":["TARGET"],"time_stamps_":["TIME_STAMP"]},"output_":{"categoricals_":["UCC","UCC1","UCC2","UCC3","UCC4","UCC5"],"discretes_":["EXPNYR","EXPNMO"],"join_keys_":["BASKETID"],"name_":"EXPD","numericals_":["COST"],"targets_":["TARGET"],"time_stamps_":["TIME_STAMP"]},"weight_":-0.048029239349124606},"child_smaller_":{"input_":{"categoricals_":["UCC","UCC1","UCC2","UCC3","UCC4","UCC5"],"discretes_":["EXPNYR","EXPNMO"],"join_keys_":["BASKETID"],"name_":"EXPD","numericals_":["COST"],"targets_":["TARGET"],"time_stamps_":["TIME_STAMP"]},"output_":{"categoricals_":["UCC","UCC1","UCC2","UCC3","UCC4","UCC5"],"discretes_":["EXPNYR","EXPNMO"],"join_keys_":["BASKETID"],"name_":"EXPD","numericals_":["COST"],"targets_":["TARGET"],"time_stamps_":["TIME_STAMP"]},"weight_":-0.006712218414624794},"column_":0,"column_input_":0,"critical_value_":0,"data_used_":"same_units_categorical","input_":{"categoricals_":["UCC","UCC1","UCC2","UCC3","UCC4","UCC5"],"discretes_":["EXPNYR","EXPNMO"],"join_keys_":["BASKETID"],"name_":"EXPD","numericals_":["COST"],"targets_":["TARGET"],"time_stamps_":["TIME_STAMP"]},"output_":{"categoricals_":["UCC","UCC1","UCC2","UCC3","UCC4","UCC5"],"discretes_":["EXPNYR","EXPNMO"],"join_keys_":["BASKETID"],"name_":"EXPD","numericals_":["COST"],"targets_":["TARGET"],"time_stamps_":["TIME_STAMP"]},"weight_":-0.008634838436715132},"column_":3,"column_input_":0,"critical_value_":0,"data_used_":"categorical_output","input_":{"categoricals_":["UCC","UCC1","UCC2","UCC3","UCC4","UCC5"],"discretes_":["EXPNYR","EXPNMO"],"join_keys_":["BASKETID"],"name_":"EXPD","numericals_":["COST"],"targets_":["TARGET"],"time_stamps_":["TIME_STAMP"]},"output_":{"categoricals_":["UCC","UCC1","UCC2","UCC3","UCC4","UCC5"],"discretes_":["EXPNYR","EXPNMO"],"join_keys_":["BASKETID"],"name_":"EXPD","numericals_":["COST"],"targets_":["TARGET"],"time_stamps_":["TIME_STAMP"]},"weight_":0.008529650607956372},"column_":0,"column_input_":0,"critical_value_":0,"data_used_":"categorical_output","input_":{"categoricals_":["UCC","UCC1","UCC2","UCC3","UCC4","UCC5"],"discretes_":["EXPNYR","EXPNMO"],"join_keys_":["BASKETID"],"name_":"EXPD","numericals_":["COST"],"targets_":["TARGET"],"time_stamps_":["TIME_STAMP"]},"output_":{"categoricals_":["UCC","UCC1","UCC2","UCC3","UCC4","UCC5"],"discretes_":["EXPNYR","EXPNMO"],"join_keys_":["BASKETID"],"name_":"EXPD","numericals_":["COST"],"targets_":["TARGET"],"time_stamps_":["TIME_STAMP"]},"weight_":0.012401776149970713},"column_":3,"column_input_":0,"critical_value_":0,"data_used_":"categorical_output","input_":{"categoricals_":["UCC","UCC1","UCC2","UCC3","UCC4","UCC5"],"discretes_":["EXPNYR","EXPNMO"],"join_keys_":["BASKETID"],"name_":"EXPD","numericals_":["COST"],"targets_":["TARGET"],"time_stamps_":["TIME_STAMP"]},"output_":{"categoricals_":["UCC","UCC1","UCC2","UCC3","UCC4","UCC5"],"discretes_":["EXPNYR","EXPNMO"],"join_keys_":["BASKETID"],"name_":"EXPD","numericals_":["COST"],"targets_":["TARGET"],"time_stamps_":["TIME_STAMP"]},"weight_":0},"update_rate_":0.15554957612939688},{"input_":{"categoricals_":["UCC","UCC1","UCC2","UCC3","UCC4","UCC5"],"discretes_":["EXPNYR","EXPNMO"],"join_keys_":["BASKETID"],"name_":"EXPD","numericals_":["COST"],"targets_":["TARGET"],"time_stamps_":["TIME_STAMP"]},"intercept_":-0.38969445452883766,"loss_":"AVG","output_":{"categoricals_":["UCC","UCC1","UCC2","UCC3","UCC4","UCC5"],"discretes_":["EXPNYR","EXPNMO"],"join_keys_":["BASKETID"],"name_":"EXPD","numericals_":["COST"],"targets_":["TARGET"],"time_stamps_":["TIME_STAMP"]},"peripheral_used_":1,"root_":{"categories_used_":[655,656,657,659,662,664,665,668,669,671,673,674,677,678,679,692,693,699,701,702,703,705,706,708,711,717,719,723,724,727,734,739,741,745,746,747,755,757,759,763,765,768,770,771,775,778,788,793,804,809,811,819,822,832,839,841,848,1356,1358,1359,1360,1361,1363,1367,1368,1369,1371,1372,1374,1376,1382,1383,1384,1386,1387,1392],"child_greater_":{"categories_used_":[554,555,557,559,560,563,564,568,569,580,591,613,614,617,1341,1343,1350],"child_greater_":{"categories_used_":[121],"child_greater_":{"input_":{"categoricals_":["UCC","UCC1","UCC2","UCC3","UCC4","UCC5"],"discretes_":["EXPNYR","EXPNMO"],"join_keys_":["BASKETID"],"name_":"EXPD","numericals_":["COST"],"targets_":["TARGET"],"time_stamps_":["TIME_STAMP"]},"output_":{"categoricals_":["UCC","UCC1","UCC2","UCC3","UCC4","UCC5"],"discretes_":["EXPNYR","EXPNMO"],"join_keys_":["BASKETID"],"name_":"EXPD","numericals_":["COST"],"targets_":["TARGET"],"time_stamps_":["TIME_STAMP"]},"weight_":-57.22033322757883},"child_smaller_":{"categories_used_":[],"child_greater_":{"input_":{"categoricals_":["UCC","UCC1","UCC2","UCC3","UCC4","UCC5"],"discretes_":["EXPNYR","EXPNMO"],"join_keys_":["BASKETID"],"name_":"EXPD","numericals_":["COST"],"targets_":["TARGET"],"time_stamps_":["TIME_STAMP"]},"output_":{"categoricals_":["UCC","UCC1","UCC2","UCC3","UCC4","UCC5"],"discretes_":["EXPNYR","EXPNMO"],"join_keys_":["BASKETID"],"name_":"EXPD","numericals_":["COST"],"targets_":["TARGET"],"time_stamps_":["TIME_STAMP"]},"weight_":3.4715226768820906},"child_smaller_":{"input_":{"categoricals_":["UCC","UCC1","UCC2","UCC3","UCC4","UCC5"],"discretes_":["EXPNYR","EXPNMO"],"join_keys_":["BASKETID"],"name_":"EXPD","numericals_":["COST"],"targets_":["TARGET"],"time_stamps_":["TIME_STAMP"]},"output_":{"categoricals_":["UCC","UCC1","UCC2","UCC3","UCC4","UCC5"],"discretes_":["EXPNYR","EXPNMO"],"join_keys_":["BASKETID"],"name_":"EXPD","numericals_":["COST"],"targets_":["TARGET"],"time_stamps_":["TIME_STAMP"]},"weight_":4.226975031870341},"column_":4,"column_input_":4,"critical_value_":0,"data_used_":"same_units_categorical","input_":{"categoricals_":["UCC","UCC1","UCC2","UCC3","UCC4","UCC5"],"discretes_":["EXPNYR","EXPNMO"],"join_keys_":["BASKETID"],"name_":"EXPD","numericals_":["COST"],"targets_":["TARGET"],"time_stamps_":["TIME_STAMP"]},"output_":{"categoricals_":["UCC","UCC1","UCC2","UCC3","UCC4","UCC5"],"discretes_":["EXPNYR","EXPNMO"],"join_keys_":["BASKETID"],"name_":"EXPD","numericals_":["COST"],"targets_":["TARGET"],"time_stamps_":["TIME_STAMP"]},"weight_":4.179241654587227},"column_":0,"column_input_":0,"critical_value_":0,"data_used_":"categorical_input","input_":{"categoricals_":["UCC","UCC1","UCC2","UCC3","UCC4","UCC5"],"discretes_":["EXPNYR","EXPNMO"],"join_keys_":["BASKETID"],"name_":"EXPD","numericals_":["COST"],"targets_":["TARGET"],"time_stamps_":["TIME_STAMP"]},"output_":{"categoricals_":["UCC","UCC1","UCC2","UCC3","UCC4","UCC5"],"discretes_":["EXPNYR","EXPNMO"],"join_keys_":["BASKETID"],"name_":"EXPD","numericals_":["COST"],"targets_":["TARGET"],"time_stamps_":["TIME_STAMP"]},"weight_":3.6880928474194845},"child_smaller_":{"categories_used_":[],"child_greater_":{"categories_used_":[478],"child_greater_":{"input_":{"categoricals_":["UCC","UCC1","UCC2","UCC3","UCC4","UCC5"],"discretes_":["EXPNYR","EXPNMO"],"join_keys_":["BASKETID"],"name_":"EXPD","numericals_":["COST"],"targets_":["TARGET"],"time_stamps_":["TIME_STAMP"]},"output_":{"categoricals_":["UCC","UCC1","UCC2","UCC3","UCC4","UCC5"],"discretes_":["EXPNYR","EXPNMO"],"join_keys_":["BASKETID"],"name_":"EXPD","numericals_":["COST"],"targets_":["TARGET"],"time_stamps_":["TIME_STAMP"]},"weight_":5.006363530442261},"child_smaller_":{"input_":{"categoricals_":["UCC","UCC1","UCC2","UCC3","UCC4","UCC5"],"discretes_":["EXPNYR","EXPNMO"],"join_keys_":["BASKETID"],"name_":"EXPD","numericals_":["COST"],"targets_":["TARGET"],"time_stamps_":["TIME_STAMP"]},"output_":{"categoricals_":["UCC","UCC1","UCC2","UCC3","UCC4","UCC5"],"discretes_":["EXPNYR","EXPNMO"],"join_keys_":["BASKETID"],"name_":"EXPD","numericals_":["COST"],"targets_":["TARGET"],"time_stamps_":["TIME_STAMP"]}},"column_":1,"column_input_":0,"critical_value_":0,"data_used_":"categorical_input","input_":{"categoricals_":["UCC","UCC1","UCC2","UCC3","UCC4","UCC5"],"discretes_":["EXPNYR","EXPNMO"],"join_keys_":["BASKETID"],"name_":"EXPD","numericals_":["COST"],"targets_":["TARGET"],"time_stamps_":["TIME_STAMP"]},"output_":{"categoricals_":["UCC","UCC1","UCC2","UCC3","UCC4","UCC5"],"discretes_":["EXPNYR","EXPNMO"],"join_keys_":["BASKETID"],"name_":"EXPD","numericals_":["COST"],"targets_":["TARGET"],"time_stamps_":["TIME_STAMP"]}},"child_smaller_":{"categories_used_":[491,493,496,500,501,502,505,508,509,510,511,512,513,517,521,522,524,530,532,535,541,1332,1334,1335,1336,1337,1338,1339,1340],"child_greater_":{"input_":{"categoricals_":["UCC","UCC1","UCC2","UCC3","UCC4","UCC5"],"discretes_":["EXPNYR","EXPNMO"],"join_keys_":["BASKETID"],"name_":"EXPD","numericals_":["COST"],"targets_":["TARGET"],"time_stamps_":["TIME_STAMP"]},"output_":{"categoricals_":["UCC","UCC1","UCC2","UCC3","UCC4","UCC5"],"discretes_":["EXPNYR","EXPNMO"],"join_keys_":["BASKETID"],"name_":"EXPD","numericals_":["COST"],"targets_":["TARGET"],"time_stamps_":["TIME_STAMP"]},"weight_":0.2717824149459291},"child_smaller_":{"input_":{"categoricals_":["UCC","UCC1","UCC2","UCC3","UCC4","UCC5"],"discretes_":["EXPNYR","EXPNMO"],"join_keys_":["BASKETID"],"name_":"EXPD","numericals_":["COST"],"targets_":["TARGET"],"time_stamps_":["TIME_STAMP"]},"output_":{"categoricals_":["UCC","UCC1","UCC2","UCC3","UCC4","UCC5"],"discretes_":["EXPNYR","EXPNMO"],"join_keys_":["BASKETID"],"name_":"EXPD","numericals_":["COST"],"targets_":["TARGET"],"time_stamps_":["TIME_STAMP"]},"weight_":3.7864285209785167},"column_":2,"column_input_":0,"critical_value_":0,"data_used_":"categorical_output","input_":{"categoricals_":["UCC","UCC1","UCC2","UCC3","UCC4","UCC5"],"discretes_":["EXPNYR","EXPNMO"],"join_keys_":["BASKETID"],"name_":"EXPD","numericals_":["COST"],"targets_":["TARGET"],"time_stamps_":["TIME_STAMP"]},"output_":{"categoricals_":["UCC","UCC1","UCC2","UCC3","UCC4","UCC5"],"discretes_":["EXPNYR","EXPNMO"],"join_keys_":["BASKETID"],"name_":"EXPD","numericals_":["COST"],"targets_":["TARGET"],"time_stamps_":["TIME_STAMP"]},"weight_":0.8297249952692208},"column_":1,"column_input_":1,"critical_value_":0,"data_used_":"same_units_categorical","input_":{"categoricals_":["UCC","UCC1","UCC2","UCC3","UCC4","UCC5"],"discretes_":["EXPNYR","EXPNMO"],"join_keys_":["BASKETID"],"name_":"EXPD","numericals_":["COST"],"targets_":["TARGET"],"time_stamps_":["TIME_STAMP"]},"output_":{"categoricals_":["UCC","UCC1","UCC2","UCC3","UCC4","UCC5"],"discretes_":["EXPNYR","EXPNMO"],"join_keys_":["BASKETID"],"name_":"EXPD","numericals_":["COST"],"targets_":["TARGET"],"time_stamps_":["TIME_STAMP"]}},"column_":3,"column_input_":0,"critical_value_":0,"data_used_":"categorical_output","input_":{"categoricals_":["UCC","UCC1","UCC2","UCC3","UCC4","UCC5"],"discretes_":["EXPNYR","EXPNMO"],"join_keys_":["BASKETID"],"name_":"EXPD","numericals_":["COST"],"targets_":["TARGET"],"time_stamps_":["TIME_STAMP"]},"output_":{"categoricals_":["UCC","UCC1","UCC2","UCC3","UCC4","UCC5"],"discretes_":["EXPNYR","EXPNMO"],"join_keys_":["BASKETID"],"name_":"EXPD","numericals_":["COST"],"targets_":["TARGET"],"time_stamps_":["TIME_STAMP"]},"weight_":6.749867101561352},"child_smaller_":{"categories_used_":[496],"child_greater_":{"categories_used_":[],"child_greater_":{"categories_used_":[],"child_greater_":{"input_":{"categoricals_":["UCC","UCC1","UCC2","UCC3","UCC4","UCC5"],"discretes_":["EXPNYR","EXPNMO"],"join_keys_":["BASKETID"],"name_":"EXPD","numericals_":["COST"],"targets_":["TARGET"],"time_stamps_":["TIME_STAMP"]},"output_":{"categoricals_":["UCC","UCC1","UCC2","UCC3","UCC4","UCC5"],"discretes_":["EXPNYR","EXPNMO"],"join_keys_":["BASKETID"],"name_":"EXPD","numericals_":["COST"],"targets_":["TARGET"],"time_stamps_":["TIME_STAMP"]}},"child_smaller_":{"input_":{"categoricals_":["UCC","UCC1","UCC2","UCC3","UCC4","UCC5"],"discretes_":["EXPNYR","EXPNMO"],"join_keys_":["BASKETID"],"name_":"EXPD","numericals_":["COST"],"targets_":["TARGET"],"time_stamps_":["TIME_STAMP"]},"output_":{"categoricals_":["UCC","UCC1","UCC2","UCC3","UCC4","UCC5"],"discretes_":["EXPNYR","EXPNMO"],"join_keys_":["BASKETID"],"name_":"EXPD","numericals_":["COST"],"targets_":["TARGET"],"time_stamps_":["TIME_STAMP"]},"weight_":0},"column_":0,"column_input_":0,"critical_value_":0,"data_used_":"numerical_output_is_nan","input_":{"categoricals_":["UCC","UCC1","UCC2","UCC3","UCC4","UCC5"],"discretes_":["EXPNYR","EXPNMO"],"join_keys_":["BASKETID"],"name_":"EXPD","numericals_":["COST"],"targets_":["TARGET"],"time_stamps_":["TIME_STAMP"]},"output_":{"categoricals_":["UCC","UCC1","UCC2","UCC3","UCC4","UCC5"],"discretes_":["EXPNYR","EXPNMO"],"join_keys_":["BASKETID"],"name_":"EXPD","numericals_":["COST"],"targets_":["TARGET"],"time_stamps_":["TIME_STAMP"]}},"child_smaller_":{"input_":{"categoricals_":["UCC","UCC1","UCC2","UCC3","UCC4","UCC5"],"discretes_":["EXPNYR","EXPNMO"],"join_keys_":["BASKETID"],"name_":"EXPD","numericals_":["COST"],"targets_":["TARGET"],"time_stamps_":["TIME_STAMP"]},"output_":{"categoricals_":["UCC","UCC1","UCC2","UCC3","UCC4","UCC5"],"discretes_":["EXPNYR","EXPNMO"],"join_keys_":["BASKETID"],"name_":"EXPD","numericals_":["COST"],"targets_":["TARGET"],"time_stamps_":["TIME_STAMP"]},"weight_":0},"column_":1,"column_input_":0,"critical_value_":0,"data_used_":"discrete_input_is_nan","input_":{"categoricals_":["UCC","UCC1","UCC2","UCC3","UCC4","UCC5"],"discretes_":["EXPNYR","EXPNMO"],"join_keys_":["BASKETID"],"name_":"EXPD","numericals_":["COST"],"targets_":["TARGET"],"time_stamps_":["TIME_STAMP"]},"output_":{"categoricals_":["UCC","UCC1","UCC2","UCC3","UCC4","UCC5"],"discretes_":["EXPNYR","EXPNMO"],"join_keys_":["BASKETID"],"name_":"EXPD","numericals_":["COST"],"targets_":["TARGET"],"time_stamps_":["TIME_STAMP"]}},"child_smaller_":{"categories_used_":[491,492,493,498,500,501,502,504,505,508,510,511,512,513,525,526,532,535,1332,1334,1335,1336,1337,1338,1339,1340],"child_greater_":{"categories_used_":[],"child_greater_":{"input_":{"categoricals_":["UCC","UCC1","UCC2","UCC3","UCC4","UCC5"],"discretes_":["EXPNYR","EXPNMO"],"join_keys_":["BASKETID"],"name_":"EXPD","numericals_":["COST"],"targets_":["TARGET"],"time_stamps_":["TIME_STAMP"]},"output_":{"categoricals_":["UCC","UCC1","UCC2","UCC3","UCC4","UCC5"],"discretes_":["EXPNYR","EXPNMO"],"join_keys_":["BASKETID"],"name_":"EXPD","numericals_":["COST"],"targets_":["TARGET"],"time_stamps_":["TIME_STAMP"]},"weight_":-2.385239966136466},"child_smaller_":{"input_":{"categoricals_":["UCC","UCC1","UCC2","UCC3","UCC4","UCC5"],"discretes_":["EXPNYR","EXPNMO"],"join_keys_":["BASKETID"],"name_":"EXPD","numericals_":["COST"],"targets_":["TARGET"],"time_stamps_":["TIME_STAMP"]},"output_":{"categoricals_":["UCC","UCC1","UCC2","UCC3","UCC4","UCC5"],"discretes_":["EXPNYR","EXPNMO"],"join_keys_":["BASKETID"],"name_":"EXPD","numericals_":["COST"],"targets_":["TARGET"],"time_stamps_":["TIME_STAMP"]},"weight_":0.11910365900643692},"column_":1,"column_input_":0,"critical_value_":6,"data_used_":"discrete_input","input_":{"categoricals_":["UCC","UCC1","UCC2","UCC3","UCC4","UCC5"],"discretes_":["EXPNYR","EXPNMO"],"join_keys_":["BASKETID"],"name_":"EXPD","numericals_":["COST"],"targets_":["TARGET"],"time_stamps_":["TIME_STAMP"]},"output_":{"categoricals_":["UCC","UCC1","UCC2","UCC3","UCC4","UCC5"],"discretes_":["EXPNYR","EXPNMO"],"join_keys_":["BASKETID"],"name_":"EXPD","numericals_":["COST"],"targets_":["TARGET"],"time_stamps_":["TIME_STAMP"]},"weight_":-0.565219853636737},"child_smaller_":{"categories_used_":[480,482],"child_greater_":{"input_":{"categoricals_":["UCC","UCC1","UCC2","UCC3","UCC4","UCC5"],"discretes_":["EXPNYR","EXPNMO"],"join_keys_":["BASKETID"],"name_":"EXPD","numericals_":["COST"],"targets_":["TARGET"],"time_stamps_":["TIME_STAMP"]},"output_":{"categoricals_":["UCC","UCC1","UCC2","UCC3","UCC4","UCC5"],"discretes_":["EXPNYR","EXPNMO"],"join_keys_":["BASKETID"],"name_":"EXPD","numericals_":["COST"],"targets_":["TARGET"],"time_stamps_":["TIME_STAMP"]}},"child_smaller_":{"input_":{"categoricals_":["UCC","UCC1","UCC2","UCC3","UCC4","UCC5"],"discretes_":["EXPNYR","EXPNMO"],"join_keys_":["BASKETID"],"name_":"EXPD","numericals_":["COST"],"targets_":["TARGET"],"time_stamps_":["TIME_STAMP"]},"output_":{"categoricals_":["UCC","UCC1","UCC2","UCC3","UCC4","UCC5"],"discretes_":["EXPNYR","EXPNMO"],"join_keys_":["BASKETID"],"name_":"EXPD","numericals_":["COST"],"targets_":["TARGET"],"time_stamps_":["TIME_STAMP"]},"weight_":-4.069090847757653},"column_":1,"column_input_":0,"critical_value_":0,"data_used_":"categorical_input","input_":{"categoricals_":["UCC","UCC1","UCC2","UCC3","UCC4","UCC5"],"discretes_":["EXPNYR","EXPNMO"],"join_keys_":["BASKETID"],"name_":"EXPD","numericals_":["COST"],"targets_":["TARGET"],"time_stamps_":["TIME_STAMP"]},"output_":{"categoricals_":["UCC","UCC1","UCC2","UCC3","UCC4","UCC5"],"discretes_":["EXPNYR","EXPNMO"],"join_keys_":["BASKETID"],"name_":"EXPD","numericals_":["COST"],"targets_":["TARGET"],"time_stamps_":["TIME_STAMP"]},"weight_":-3.2165865894155283},"column_":2,"column_input_":0,"critical_value_":0,"data_used_":"categorical_output","input_":{"categoricals_":["UCC","UCC1","UCC2","UCC3","UCC4","UCC5"],"discretes_":["EXPNYR","EXPNMO"],"join_keys_":["BASKETID"],"name_":"EXPD","numericals_":["COST"],"targets_":["TARGET"],"time_stamps_":["TIME_STAMP"]},"output_":{"categoricals_":["UCC","UCC1","UCC2","UCC3","UCC4","UCC5"],"discretes_":["EXPNYR","EXPNMO"],"join_keys_":["BASKETID"],"name_":"EXPD","numericals_":["COST"],"targets_":["TARGET"],"time_stamps_":["TIME_STAMP"]},"weight_":-1.5290222506322495},"column_":2,"column_input_":0,"critical_value_":0,"data_used_":"categorical_output","input_":{"categoricals_":["UCC","UCC1","UCC2","UCC3","UCC4","UCC5"],"discretes_":["EXPNYR","EXPNMO"],"join_keys_":["BASKETID"],"name_":"EXPD","numericals_":["COST"],"targets_":["TARGET"],"time_stamps_":["TIME_STAMP"]},"output_":{"categoricals_":["UCC","UCC1","UCC2","UCC3","UCC4","UCC5"],"discretes_":["EXPNYR","EXPNMO"],"join_keys_":["BASKETID"],"name_":"EXPD","numericals_":["COST"],"targets_":["TARGET"],"time_stamps_":["TIME_STAMP"]},"weight_":0},"column_":4,"column_input_":0,"critical_value_":0,"data_used_":"categorical_input","input_":{"categoricals_":["UCC","UCC1","UCC2","UCC3","UCC4","UCC5"],"discretes_":["EXPNYR","EXPNMO"],"join_keys_":["BASKETID"],"name_":"EXPD","numericals_":["COST"],"targets_":["TARGET"],"time_stamps_":["TIME_STAMP"]},"output_":{"categoricals_":["UCC","UCC1","UCC2","UCC3","UCC4","UCC5"],"discretes_":["EXPNYR","EXPNMO"],"join_keys_":["BASKETID"],"name_":"EXPD","numericals_":["COST"],"targets_":["TARGET"],"time_stamps_":["TIME_STAMP"]},"weight_":0},"update_rate_":0.3244955661456613},{"input_":{"categoricals_":["UCC","UCC1","UCC2","UCC3","UCC4","UCC5"],"discretes_":["EXPNYR","EXPNMO"],"join_keys_":["BASKETID"],"name_":"EXPD","numericals_":["COST"],"targets_":["TARGET"],"time_stamps_":["TIME_STAMP"]},"intercept_":-0.347133855126195,"loss_":"AVG","output_":{"categoricals_":["UCC","UCC1","UCC2","UCC3","UCC4","UCC5"],"discretes_":["EXPNYR","EXPNMO"],"join_keys_":["BASKETID"],"name_":"EXPD","numericals_":["COST"],"targets_":["TARGET"],"time_stamps_":["TIME_STAMP"]},"peripheral_used_":1,"root_":{"categories_used_":[1350],"child_greater_":{"input_":{"categoricals_":["UCC","UCC1","UCC2","UCC3","UCC4","UCC5"],"discretes_":["EXPNYR","EXPNMO"],"join_keys_":["BASKETID"],"name_":"EXPD","numericals_":["COST"],"targets_":["TARGET"],"time_stamps_":["TIME_STAMP"]},"output_":{"categoricals_":["UCC","UCC1","UCC2","UCC3","UCC4","UCC5"],"discretes_":["EXPNYR","EXPNMO"],"join_keys_":["BASKETID"],"name_":"EXPD","numericals_":["COST"],"targets_":["TARGET"],"time_stamps_":["TIME_STAMP"]},"weight_":2.0042048031200665},"child_smaller_":{"categories_used_":[500],"child_greater_":{"categories_used_":[477],"child_greater_":{"input_":{"categoricals_":["UCC","UCC1","UCC2","UCC3","UCC4","UCC5"],"discretes_":["EXPNYR","EXPNMO"],"join_keys_":["BASKETID"],"name_":"EXPD","numericals_":["COST"],"targets_":["TARGET"],"time_stamps_":["TIME_STAMP"]},"output_":{"categoricals_":["UCC","UCC1","UCC2","UCC3","UCC4","UCC5"],"discretes_":["EXPNYR","EXPNMO"],"join_keys_":["BASKETID"],"name_":"EXPD","numericals_":["COST"],"targets_":["TARGET"],"time_stamps_":["TIME_STAMP"]},"weight_":0.4934789314436207},"child_smaller_":{"input_":{"categoricals_":["UCC","UCC1","UCC2","UCC3","UCC4","UCC5"],"discretes_":["EXPNYR","EXPNMO"],"join_keys_":["BASKETID"],"name_":"EXPD","numericals_":["COST"],"targets_":["TARGET"],"time_stamps_":["TIME_STAMP"]},"output_":{"categoricals_":["UCC","UCC1","UCC2","UCC3","UCC4","UCC5"],"discretes_":["EXPNYR","EXPNMO"],"join_keys_":["BASKETID"],"name_":"EXPD","numericals_":["COST"],"targets_":["TARGET"],"time_stamps_":["TIME_STAMP"]},"weight_":1.9506818352480733},"column_":1,"column_input_":0,"critical_value_":0,"data_used_":"categorical_output","input_":{"categoricals_":["UCC","UCC1","UCC2","UCC3","UCC4","UCC5"],"discretes_":["EXPNYR","EXPNMO"],"join_keys_":["BASKETID"],"name_":"EXPD","numericals_":["COST"],"targets_":["TARGET"],"time_stamps_":["TIME_STAMP"]},"output_":{"categoricals_":["UCC","UCC1","UCC2","UCC3","UCC4","UCC5"],"discretes_":["EXPNYR","EXPNMO"],"join_keys_":["BASKETID"],"name_":"EXPD","numericals_":["COST"],"targets_":["TARGET"],"time_stamps_":["TIME_STAMP"]},"weight_":1.3410781422163152},"child_smaller_":{"categories_used_":[1371],"child_greater_":{"categories_used_":[477],"child_greater_":{"input_":{"categoricals_":["UCC","UCC1","UCC2","UCC3","UCC4","UCC5"],"discretes_":["EXPNYR","EXPNMO"],"join_keys_":["BASKETID"],"name_":"EXPD","numericals_":["COST"],"targets_":["TARGET"],"time_stamps_":["TIME_STAMP"]},"output_":{"categoricals_":["UCC","UCC1","UCC2","UCC3","UCC4","UCC5"],"discretes_":["EXPNYR","EXPNMO"],"join_keys_":["BASKETID"],"name_":"EXPD","numericals_":["COST"],"targets_":["TARGET"],"time_stamps_":["TIME_STAMP"]},"weight_":-0.6937666833323153},"child_smaller_":{"input_":{"categoricals_":["UCC","UCC1","UCC2","UCC3","UCC4","UCC5"],"discretes_":["EXPNYR","EXPNMO"],"join_keys_":["BASKETID"],"name_":"EXPD","numericals_":["COST"],"targets_":["TARGET"],"time_stamps_":["TIME_STAMP"]},"output_":{"categoricals_":["UCC","UCC1","UCC2","UCC3","UCC4","UCC5"],"discretes_":["EXPNYR","EXPNMO"],"join_keys_":["BASKETID"],"name_":"EXPD","numericals_":["COST"],"targets_":["TARGET"],"time_stamps_":["TIME_STAMP"]},"weight_":-0.4302431087059462},"column_":1,"column_input_":0,"critical_value_":0,"data_used_":"categorical_output","input_":{"categoricals_":["UCC","UCC1","UCC2","UCC3","UCC4","UCC5"],"discretes_":["EXPNYR","EXPNMO"],"join_keys_":["BASKETID"],"name_":"EXPD","numericals_":["COST"],"targets_":["TARGET"],"time_stamps_":["TIME_STAMP"]},"output_":{"categoricals_":["UCC","UCC1","UCC2","UCC3","UCC4","UCC5"],"discretes_":["EXPNYR","EXPNMO"],"join_keys_":["BASKETID"],"name_":"EXPD","numericals_":["COST"],"targets_":["TARGET"],"time_stamps_":["TIME_STAMP"]},"weight_":-0.5604731966759452},"child_smaller_":{"categories_used_":[1367],"child_greater_":{"input_":{"categoricals_":["UCC","UCC1","UCC2","UCC3","UCC4","UCC5"],"discretes_":["EXPNYR","EXPNMO"],"join_keys_":["BASKETID"],"name_":"EXPD","numericals_":["COST"],"targets_":["TARGET"],"time_stamps_":["TIME_STAMP"]},"output_":{"categoricals_":["UCC","UCC1","UCC2","UCC3","UCC4","UCC5"],"discretes_":["EXPNYR","EXPNMO"],"join_keys_":["BASKETID"],"name_":"EXPD","numericals_":["COST"],"targets_":["TARGET"],"time_stamps_":["TIME_STAMP"]},"weight_":-0.6991037238273012},"child_smaller_":{"input_":{"categoricals_":["UCC","UCC1","UCC2","UCC3","UCC4","UCC5"],"discretes_":["EXPNYR","EXPNMO"],"join_keys_":["BASKETID"],"name_":"EXPD","numericals_":["COST"],"targets_":["TARGET"],"time_stamps_":["TIME_STAMP"]},"output_":{"categoricals_":["UCC","UCC1","UCC2","UCC3","UCC4","UCC5"],"discretes_":["EXPNYR","EXPNMO"],"join_keys_":["BASKETID"],"name_":"EXPD","numericals_":["COST"],"targets_":["TARGET"],"time_stamps_":["TIME_STAMP"]}},"column_":4,"column_input_":0,"critical_value_":0,"data_used_":"categorical_input","input_":{"categoricals_":["UCC","UCC1","UCC2","UCC3","UCC4","UCC5"],"discretes_":["EXPNYR","EXPNMO"],"join_keys_":["BASKETID"],"name_":"EXPD","numericals_":["COST"],"targets_":["TARGET"],"time_stamps_":["TIME_STAMP"]},"output_":{"categoricals_":["UCC","UCC1","UCC2","UCC3","UCC4","UCC5"],"discretes_":["EXPNYR","EXPNMO"],"join_keys_":["BASKETID"],"name_":"EXPD","numericals_":["COST"],"targets_":["TARGET"],"time_stamps_":["TIME_STAMP"]}},"column_":4,"column_input_":0,"critical_value_":0,"data_used_":"categorical_input","input_":{"categoricals_":["UCC","UCC1","UCC2","UCC3","UCC4","UCC5"],"discretes_":["EXPNYR","EXPNMO"],"join_keys_":["BASKETID"],"name_":"EXPD","numericals_":["COST"],"targets_":["TARGET"],"time_stamps_":["TIME_STAMP"]},"output_":{"categoricals_":["UCC","UCC1","UCC2","UCC3","UCC4","UCC5"],"discretes_":["EXPNYR","EXPNMO"],"join_keys_":["BASKETID"],"name_":"EXPD","numericals_":["COST"],"targets_":["TARGET"],"time_stamps_":["TIME_STAMP"]}},"column_":2,"column_input_":0,"critical_value_":0,"data_used_":"categorical_input","input_":{"categoricals_":["UCC","UCC1","UCC2","UCC3","UCC4","UCC5"],"discretes_":["EXPNYR","EXPNMO"],"join_keys_":["BASKETID"],"name_":"EXPD","numericals_":["COST"],"targets_":["TARGET"],"time_stamps_":["TIME_STAMP"]},"output_":{"categoricals_":["UCC","UCC1","UCC2","UCC3","UCC4","UCC5"],"discretes_":["EXPNYR","EXPNMO"],"join_keys_":["BASKETID"],"name_":"EXPD","numericals_":["COST"],"targets_":["TARGET"],"time_stamps_":["TIME_STAMP"]}},"column_":3,"column_input_":0,"critical_value_":0,"data_used_":"categorical_input","input_":{"categoricals_":["UCC","UCC1","UCC2","UCC3","UCC4","UCC5"],"discretes_":["EXPNYR","EXPNMO"],"join_keys_":["BASKETID"],"name_":"EXPD","numericals_":["COST"],"targets_":["TARGET"],"time_stamps_":["TIME_STAMP"]},"output_":{"categoricals_":["UCC","UCC1","UCC2","UCC3","UCC4","UCC5"],"discretes_":["EXPNYR","EXPNMO"],"join_keys_":["BASKETID"],"name_":"EXPD","numericals_":["COST"],"targets_":["TARGET"],"time_stamps_":["TIME_STAMP"]},"weight_":0},"update_rate_":0.5385683997238093},{"input_":{"categoricals_":["UCC","UCC1","UCC2","UCC3","UCC4","UCC5"],"discretes_":["EXPNYR","EXPNMO"],"join_keys_":["BASKETID"],"name_":"EXPD","numericals_":["COST"],"targets_":["TARGET"],"time_stamps_":["TIME_STAMP"]},"intercept_":1.9829575152504266,"loss_":"AVG","output_":{"categoricals_":["UCC","UCC1","UCC2","UCC3","UCC4","UCC5"],"discretes_":["EXPNYR","EXPNMO"],"join_keys_":["BASKETID"],"name_":"EXPD","numericals_":["COST"],"targets_":["TARGET"],"time_stamps_":["TIME_STAMP"]},"peripheral_used_":1,"root_":{"categories_used_":[486,491,498,499,502,503,511,514,517,518,522,524,525,526,528,529,530,534,539,540,541,542,1331,1335,1339,1340],"child_greater_":{"categories_used_":[660,673,705,727,741,747,763,799,808,832,833,1382,1387,1392],"child_greater_":{"categories_used_":[129],"child_greater_":{"categories_used_":[477],"child_greater_":{"input_":{"categoricals_":["UCC","UCC1","UCC2","UCC3","UCC4","UCC5"],"discretes_":["EXPNYR","EXPNMO"],"join_keys_":["BASKETID"],"name_":"EXPD","numericals_":["COST"],"targets_":["TARGET"],"time_stamps_":["TIME_STAMP"]},"output_":{"categoricals_":["UCC","UCC1","UCC2","UCC3","UCC4","UCC5"],"discretes_":["EXPNYR","EXPNMO"],"join_keys_":["BASKETID"],"name_":"EXPD","numericals_":["COST"],"targets_":["TARGET"],"time_stamps_":["TIME_STAMP"]},"weight_":-3.1574055155061327},"child_smaller_":{"input_":{"categoricals_":["UCC","UCC1","UCC2","UCC3","UCC4","UCC5"],"discretes_":["EXPNYR","EXPNMO"],"join_keys_":["BASKETID"],"name_":"EXPD","numericals_":["COST"],"targets_":["TARGET"],"time_stamps_":["TIME_STAMP"]},"output_":{"categoricals_":["UCC","UCC1","UCC2","UCC3","UCC4","UCC5"],"discretes_":["EXPNYR","EXPNMO"],"join_keys_":["BASKETID"],"name_":"EXPD","numericals_":["COST"],"targets_":["TARGET"],"time_stamps_":["TIME_STAMP"]},"weight_":-3.150461432935551},"column_":1,"column_input_":0,"critical_value_":0,"data_used_":"categorical_input","input_":{"categoricals_":["UCC","UCC1","UCC2","UCC3","UCC4","UCC5"],"discretes_":["EXPNYR","EXPNMO"],"join_keys_":["BASKETID"],"name_":"EXPD","numericals_":["COST"],"targets_":["TARGET"],"time_stamps_":["TIME_STAMP"]},"output_":{"categoricals_":["UCC","UCC1","UCC2","UCC3","UCC4","UCC5"],"discretes_":["EXPNYR","EXPNMO"],"join_keys_":["BASKETID"],"name_":"EXPD","numericals_":["COST"],"targets_":["TARGET"],"time_stamps_":["TIME_STAMP"]},"weight_":-3.1534987736706204},"child_smaller_":{"categories_used_":[1392],"child_greater_":{"input_":{"categoricals_":["UCC","UCC1","UCC2","UCC3","UCC4","UCC5"],"discretes_":["EXPNYR","EXPNMO"],"join_keys_":["BASKETID"],"name_":"EXPD","numericals_":["COST"],"targets_":["TARGET"],"time_stamps_":["TIME_STAMP"]},"output_":{"categoricals_":["UCC","UCC1","UCC2","UCC3","UCC4","UCC5"],"discretes_":["EXPNYR","EXPNMO"],"join_keys_":["BASKETID"],"name_":"EXPD","numericals_":["COST"],"targets_":["TARGET"],"time_stamps_":["TIME_STAMP"]},"weight_":8.02482942036685},"child_smaller_":{"input_":{"categoricals_":["UCC","UCC1","UCC2","UCC3","UCC4","UCC5"],"discretes_":["EXPNYR","EXPNMO"],"join_keys_":["BASKETID"],"name_":"EXPD","numericals_":["COST"],"targets_":["TARGET"],"time_stamps_":["TIME_STAMP"]},"output_":{"categoricals_":["UCC","UCC1","UCC2","UCC3","UCC4","UCC5"],"discretes_":["EXPNYR","EXPNMO"],"join_keys_":["BASKETID"],"name_":"EXPD","numericals_":["COST"],"targets_":["TARGET"],"time_stamps_":["TIME_STAMP"]}},"column_":4,"column_input_":0,"critical_value_":0,"data_used_":"categorical_output","input_":{"categoricals_":["UCC","UCC1","UCC2","UCC3","UCC4","UCC5"],"discretes_":["EXPNYR","EXPNMO"],"join_keys_":["BASKETID"],"name_":"EXPD","numericals_":["COST"],"targets_":["TARGET"],"time_stamps_":["TIME_STAMP"]},"output_":{"categoricals_":["UCC","UCC1","UCC2","UCC3","UCC4","UCC5"],"discretes_":["EXPNYR","EXPNMO"],"join_keys_":["BASKETID"],"name_":"EXPD","numericals_":["COST"],"targets_":["TARGET"],"time_stamps_":["TIME_STAMP"]}},"column_":0,"column_input_":0,"critical_value_":0,"data_used_":"categorical_output","input_":{"categoricals_":["UCC","UCC1","UCC2","UCC3","UCC4","UCC5"],"discretes_":["EXPNYR","EXPNMO"],"join_keys_":["BASKETID"],"name_":"EXPD","numericals_":["COST"],"targets_":["TARGET"],"time_stamps_":["TIME_STAMP"]},"output_":{"categoricals_":["UCC","UCC1","UCC2","UCC3","UCC4","UCC5"],"discretes_":["EXPNYR","EXPNMO"],"join_keys_":["BASKETID"],"name_":"EXPD","numericals_":["COST"],"targets_":["TARGET"],"time_stamps_":["TIME_STAMP"]}},"child_smaller_":{"categories_used_":[486,491,498,499,502,503,511,514,517,518,522,524,525,526,528,529,530,534,539,540,541,1331,1335,1339,1340],"child_greater_":{"categories_used_":[486,518,528,529,1335],"child_greater_":{"input_":{"categoricals_":["UCC","UCC1","UCC2","UCC3","UCC4","UCC5"],"discretes_":["EXPNYR","EXPNMO"],"join_keys_":["BASKETID"],"name_":"EXPD","numericals_":["COST"],"targets_":["TARGET"],"time_stamps_":["TIME_STAMP"]},"output_":{"categoricals_":["UCC","UCC1","UCC2","UCC3","UCC4","UCC5"],"discretes_":["EXPNYR","EXPNMO"],"join_keys_":["BASKETID"],"name_":"EXPD","numericals_":["COST"],"targets_":["TARGET"],"time_stamps_":["TIME_STAMP"]},"weight_":-0.8984501393762183},"child_smaller_":{"input_":{"categoricals_":["UCC","UCC1","UCC2","UCC3","UCC4","UCC5"],"discretes_":["EXPNYR","EXPNMO"],"join_keys_":["BASKETID"],"name_":"EXPD","numericals_":["COST"],"targets_":["TARGET"],"time_stamps_":["TIME_STAMP"]},"output_":{"categoricals_":["UCC","UCC1","UCC2","UCC3","UCC4","UCC5"],"discretes_":["EXPNYR","EXPNMO"],"join_keys_":["BASKETID"],"name_":"EXPD","numericals_":["COST"],"targets_":["TARGET"],"time_stamps_":["TIME_STAMP"]},"weight_":-3.003049022873966},"column_":2,"column_input_":0,"critical_value_":0,"data_used_":"categorical_output","input_":{"categoricals_":["UCC","UCC1","UCC2","UCC3","UCC4","UCC5"],"discretes_":["EXPNYR","EXPNMO"],"join_keys_":["BASKETID"],"name_":"EXPD","numericals_":["COST"],"targets_":["TARGET"],"time_stamps_":["TIME_STAMP"]},"output_":{"categoricals_":["UCC","UCC1","UCC2","UCC3","UCC4","UCC5"],"discretes_":["EXPNYR","EXPNMO"],"join_keys_":["BASKETID"],"name_":"EXPD","numericals_":["COST"],"targets_":["TARGET"],"time_stamps_":["TIME_STAMP"]},"weight_":-2.446904335607062},"child_smaller_":{"input_":{"categoricals_":["UCC","UCC1","UCC2","UCC3","UCC4","UCC5"],"discretes_":["EXPNYR","EXPNMO"],"join_keys_":["BASKETID"],"name_":"EXPD","numericals_":["COST"],"targets_":["TARGET"],"time_stamps_":["TIME_STAMP"]},"output_":{"categoricals_":["UCC","UCC1","UCC2","UCC3","UCC4","UCC5"],"discretes_":["EXPNYR","EXPNMO"],"join_keys_":["BASKETID"],"name_":"EXPD","numericals_":["COST"],"targets_":["TARGET"],"time_stamps_":["TIME_STAMP"]},"weight_":14.21325555115232},"column_":2,"column_input_":0,"critical_value_":0,"data_used_":"categorical_output","input_":{"categoricals_":["UCC","UCC1","UCC2","UCC3","UCC4","UCC5"],"discretes_":["EXPNYR","EXPNMO"],"join_keys_":["BASKETID"],"name_":"EXPD","numericals_":["COST"],"targets_":["TARGET"],"time_stamps_":["TIME_STAMP"]},"output_":{"categoricals_":["UCC","UCC1","UCC2","UCC3","UCC4","UCC5"],"discretes_":["EXPNYR","EXPNMO"],"join_keys_":["BASKETID"],"name_":"EXPD","numericals_":["COST"],"targets_":["TARGET"],"time_stamps_":["TIME_STAMP"]},"weight_":-2.3724380879193117},"column_":4,"column_input_":0,"critical_value_":0,"data_used_":"categorical_output","input_":{"categoricals_":["UCC","UCC1","UCC2","UCC3","UCC4","UCC5"],"discretes_":["EXPNYR","EXPNMO"],"join_keys_":["BASKETID"],"name_":"EXPD","numericals_":["COST"],"targets_":["TARGET"],"time_stamps_":["TIME_STAMP"]},"output_":{"categoricals_":["UCC","UCC1","UCC2","UCC3","UCC4","UCC5"],"discretes_":["EXPNYR","EXPNMO"],"join_keys_":["BASKETID"],"name_":"EXPD","numericals_":["COST"],"targets_":["TARGET"],"time_stamps_":["TIME_STAMP"]},"weight_":0},"child_smaller_":{"input_":{"categoricals_":["UCC","UCC1","UCC2","UCC3","UCC4","UCC5"],"discretes_":["EXPNYR","EXPNMO"],"join_keys_":["BASKETID"],"name_":"EXPD","numericals_":["COST"],"targets_":["TARGET"],"time_stamps_":["TIME_STAMP"]},"output_":{"categoricals_":["UCC","UCC1","UCC2","UCC3","UCC4","UCC5"],"discretes_":["EXPNYR","EXPNMO"],"join_keys_":["BASKETID"],"name_":"EXPD","numericals_":["COST"],"targets_":["TARGET"],"time_stamps_":["TIME_STAMP"]},"weight_":-2.3084086827692163},"column_":2,"column_input_":0,"critical_value_":0,"data_used_":"categorical_output","input_":{"categoricals_":["UCC","UCC1","UCC2","UCC3","UCC4","UCC5"],"discretes_":["EXPNYR","EXPNMO"],"join_keys_":["BASKETID"],"name_":"EXPD","numericals_":["COST"],"targets_":["TARGET"],"time_stamps_":["TIME_STAMP"]},"output_":{"categoricals_":["UCC","UCC1","UCC2","UCC3","UCC4","UCC5"],"discretes_":["EXPNYR","EXPNMO"],"join_keys_":["BASKETID"],"name_":"EXPD","numericals_":["COST"],"targets_":["TARGET"],"time_stamps_":["TIME_STAMP"]},"weight_":0},"update_rate_":0.6110437882608265}]}