{"hyperparameters_":{"eta_":0.3,"gamma_":1,"lambda_":0,"max_depth_":3,"num_features_":10,"objective_":"SquareLoss","seed_":5843,"silent_":true,"sampling_factor_":1,"use_timestamps_":true},"initial_prediction_":91.626,"trees_":[{"intercept_":-91.69195955727916,"loss_":"SUM","root_":{"categories_used_":[],"child_greater_":{"weight_":0.00047490773545215794},"child_smaller_":{"weight_":1.0015532237306484},"column_":0,"column_input_":0,"critical_value_":0.49895958556758524,"data_used_":"time_stamps_diff","weight_":0},"update_rate_":1.0005183750703157},{"intercept_":-64.1314819336579,"loss_":"SUM","root_":{"categories_used_":[],"child_greater_":{"weight_":-0.0010395846106591288},"child_smaller_":{"weight_":0.6998728323609258},"column_":0,"column_input_":0,"critical_value_":0.5002693906619611,"data_used_":"time_stamps_diff","weight_":0},"update_rate_":1.0001479617880127},{"intercept_":-44.93199047890945,"loss_":"SUM","root_":{"categories_used_":[],"child_greater_":{"weight_":0.0008787065150902203},"child_smaller_":{"weight_":0.4907028506847179},"column_":0,"column_input_":0,"critical_value_":0.49895958556758524,"data_used_":"time_stamps_diff","weight_":0},"update_rate_":0.9999065922385477},{"intercept_":-31.448308648336226,"loss_":"SUM","root_":{"categories_used_":[],"child_greater_":{"weight_":0.00028986948509277134},"child_smaller_":{"weight_":0.34360122513967745},"column_":0,"column_input_":0,"critical_value_":0.49927607306782845,"data_used_":"time_stamps_diff","weight_":0},"update_rate_":0.9992992633045207},{"intercept_":-21.938688187821597,"loss_":"SUM","root_":{"categories_used_":[],"child_greater_":{"weight_":-0.0015768904180901353},"child_smaller_":{"weight_":0.2385575047487724},"column_":0,"column_input_":0,"critical_value_":0.5041040013806969,"data_used_":"time_stamps_diff","weight_":0},"update_rate_":1.0003352067598001},{"intercept_":-15.388041441486605,"loss_":"SUM","root_":{"categories_used_":[],"child_greater_":{"weight_":-0.0014864851415181928},"child_smaller_":{"weight_":0.167953570250376},"column_":0,"column_input_":0,"critical_value_":0.502821016521482,"data_used_":"time_stamps_diff","weight_":0},"update_rate_":0.9985653055081201},{"intercept_":-10.816488793809494,"loss_":"SUM","root_":{"categories_used_":[],"child_greater_":{"weight_":0.00039421471337762205},"child_smaller_":{"weight_":0.11821610134874183},"column_":0,"column_input_":0,"critical_value_":0.49780118456512806,"data_used_":"time_stamps_diff","weight_":0},"update_rate_":0.9983117028669167},{"intercept_":-7.520430761457839,"loss_":"SUM","root_":{"categories_used_":[],"child_greater_":{"weight_":-0.00018536300003831128},"child_smaller_":{"weight_":0.08173750154698957},"column_":0,"column_input_":0,"critical_value_":0.5040000841788457,"data_used_":"time_stamps_diff","weight_":0},"update_rate_":0.9994180900265612},{"intercept_":-5.267755543637409,"loss_":"AVG","root_":{"categories_used_":[],"child_greater_":{"weight_":8.625973958115638},"child_smaller_":{"weight_":1.038623460321965},"column_":0,"column_input_":0,"critical_value_":0.14691652805734234,"data_used_":"time_stamps_diff","weight_":0},"update_rate_":0.9844963747887232},{"intercept_":-3.711929672840982,"loss_":"AVG","root_":{"categories_used_":[],"child_greater_":{"weight_":6.450822585109439},"child_smaller_":{"weight_":1.2247997665904837},"column_":0,"column_input_":0,"critical_value_":0.19230772534236507,"data_used_":"time_stamps_diff","weight_":0},"update_rate_":0.9952839622092073}]}